Workbook

Sheet List
B2: RECENT KEI RESEARCH PROJECTS
B4: Type | C4: Title | D4: PI | E4: Primary Focus | F4: Secondary Focus | G4: Project Start | H4: Project End
A5: ='DB1'!$C2 -> 2023-066 | B5: {=_xlfn.IFS(LEFT($A5,2)='DB2'!$G$43,'DB2'!$F$43,LEFT($A5,2)='DB2'!$G$44,'DB2'!$F$44,LEFT($A5,2)='DB2'!$H$44,'DB2'!$F$44,LEFT($A5,2)='DB2'!$I$44,'DB2'!$F$44,LEFT($A5,2)='DB2'!$J$44,'DB2'!$F$44,LEFT($A5,2)='DB2'!$G$45,'DB2'!$F$45,LEFT($A5,2)='DB2'!$G$46,'DB2'!$F$46,LEFT($A5,2)=LEFT('DB2'!$G$47,2),'DB2'!$F$47)} -> Commissioned Research | C5: =VLOOKUP($A5,'DB1'!$C:$Q,12,0) -> Supporting Danyang’s Bid for UNESCO Global Geopark Status | D5: =VLOOKUP($A5,'DB1'!$C:$Q,13,0) -> Lee, Soojae | E5: =VLOOKUP($A5,'DB1'!$C:$Q,14,0) -> Ecology | F5: =VLOOKUP($A5,'DB1'!$C:$Q,15,0) -> Land Management and Environment | G5: =VLOOKUP($A5,'DB1'!$C:$Q,9,0) -> 45054 | H5: =VLOOKUP($A5,'DB1'!$C:$Q,10,0) -> 45713
A6: ='DB1'!$C3 -> 2023-067 | B6: {=_xlfn.IFS(LEFT($A6,2)='DB2'!$G$43,'DB2'!$F$43,LEFT($A6,2)='DB2'!$G$44,'DB2'!$F$44,LEFT($A6,2)='DB2'!$H$44,'DB2'!$F$44,LEFT($A6,2)='DB2'!$I$44,'DB2'!$F$44,LEFT($A6,2)='DB2'!$J$44,'DB2'!$F$44,LEFT($A6,2)='DB2'!$G$45,'DB2'!$F$45,LEFT($A6,2)='DB2'!$G$46,'DB2'!$F$46,LEFT($A6,2)=LEFT('DB2'!$G$47,2),'DB2'!$F$47)} -> Commissioned Research | C6: =VLOOKUP($A6,'DB1'!$C:$Q,12,0) -> Supporting Baengnyeong–Daecheong’s Bid for UNESCO Global Geopark Status | D6: =VLOOKUP($A6,'DB1'!$C:$Q,13,0) -> Lee, Soojae | E6: =VLOOKUP($A6,'DB1'!$C:$Q,14,0) -> Ecology | F6: =VLOOKUP($A6,'DB1'!$C:$Q,15,0) -> Land management and environment | G6: =VLOOKUP($A6,'DB1'!$C:$Q,9,0) -> 45056 | H6: =VLOOKUP($A6,'DB1'!$C:$Q,10,0) -> 46275
A7: ='DB1'!$C4 -> 2023-111 | B7: {=_xlfn.IFS(LEFT($A7,2)='DB2'!$G$43,'DB2'!$F$43,LEFT($A7,2)='DB2'!$G$44,'DB2'!$F$44,LEFT($A7,2)='DB2'!$H$44,'DB2'!$F$44,LEFT($A7,2)='DB2'!$I$44,'DB2'!$F$44,LEFT($A7,2)='DB2'!$J$44,'DB2'!$F$44,LEFT($A7,2)='DB2'!$G$45,'DB2'!$F$45,LEFT($A7,2)='DB2'!$G$46,'DB2'!$F$46,LEFT($A7,2)=LEFT('DB2'!$G$47,2),'DB2'!$F$47)} -> Commissioned Research | C7: =VLOOKUP($A7,'DB1'!$C:$Q,12,0) -> Consulting Service for Promoting Community Acceptance of Offshore Wind Power and Strengthening Stakeholder Capacities in Gunsan | D7: =VLOOKUP($A7,'DB1'!$C:$Q,13,0) -> Cho, Kongjang | E7: =VLOOKUP($A7,'DB1'!$C:$Q,14,0) -> Socio-Environmental Interface | F7: =VLOOKUP($A7,'DB1'!$C:$Q,15,0) -> Climate Environment (GHG Reduction) | G7: =VLOOKUP($A7,'DB1'!$C:$Q,9,0) -> 45287 | H7: =VLOOKUP($A7,'DB1'!$C:$Q,10,0) -> 45961
A8: ='DB1'!$C5 -> 2024-020 | B8: {=_xlfn.IFS(LEFT($A8,2)='DB2'!$G$43,'DB2'!$F$43,LEFT($A8,2)='DB2'!$G$44,'DB2'!$F$44,LEFT($A8,2)='DB2'!$H$44,'DB2'!$F$44,LEFT($A8,2)='DB2'!$I$44,'DB2'!$F$44,LEFT($A8,2)='DB2'!$J$44,'DB2'!$F$44,LEFT($A8,2)='DB2'!$G$45,'DB2'!$F$45,LEFT($A8,2)='DB2'!$G$46,'DB2'!$F$46,LEFT($A8,2)=LEFT('DB2'!$G$47,2),'DB2'!$F$47)} -> Commissioned Research | C8: =VLOOKUP($A8,'DB1'!$C:$Q,12,0) -> A Study on Science-Based Approaches to Full-Cycle Management of Environmental Restoration | D8: =VLOOKUP($A8,'DB1'!$C:$Q,13,0) -> Son, Seungwoo | E8: =VLOOKUP($A8,'DB1'!$C:$Q,14,0) -> Land Management and Environment | F8: =VLOOKUP($A8,'DB1'!$C:$Q,15,0) -> Ecology | G8: =VLOOKUP($A8,'DB1'!$C:$Q,9,0) -> 45309 | H8: =VLOOKUP($A8,'DB1'!$C:$Q,10,0) -> 45673
A9: ='DB1'!$C6 -> 2024-032 | B9: {=_xlfn.IFS(LEFT($A9,2)='DB2'!$G$43,'DB2'!$F$43,LEFT($A9,2)='DB2'!$G$44,'DB2'!$F$44,LEFT($A9,2)='DB2'!$H$44,'DB2'!$F$44,LEFT($A9,2)='DB2'!$I$44,'DB2'!$F$44,LEFT($A9,2)='DB2'!$J$44,'DB2'!$F$44,LEFT($A9,2)='DB2'!$G$45,'DB2'!$F$45,LEFT($A9,2)='DB2'!$G$46,'DB2'!$F$46,LEFT($A9,2)=LEFT('DB2'!$G$47,2),'DB2'!$F$47)} -> Commissioned Research | C9: =VLOOKUP($A9,'DB1'!$C:$Q,12,0) -> A Study on the Effectiveness of African Swine Fever (ASF) Fencing and Strategies for Improved Management | D9: =VLOOKUP($A9,'DB1'!$C:$Q,13,0) -> Koo, Kyung Ah | E9: =VLOOKUP($A9,'DB1'!$C:$Q,14,0) -> Environmental Health | F9: =VLOOKUP($A9,'DB1'!$C:$Q,15,0) -> Ecology | G9: =VLOOKUP($A9,'DB1'!$C:$Q,9,0) -> 45390 | H9: =VLOOKUP($A9,'DB1'!$C:$Q,10,0) -> 45815
A10: ='DB1'!$C7 -> 2024-036(R) | B10: {=_xlfn.IFS(LEFT($A10,2)='DB2'!$G$43,'DB2'!$F$43,LEFT($A10,2)='DB2'!$G$44,'DB2'!$F$44,LEFT($A10,2)='DB2'!$H$44,'DB2'!$F$44,LEFT($A10,2)='DB2'!$I$44,'DB2'!$F$44,LEFT($A10,2)='DB2'!$J$44,'DB2'!$F$44,LEFT($A10,2)='DB2'!$G$45,'DB2'!$F$45,LEFT($A10,2)='DB2'!$G$46,'DB2'!$F$46,LEFT($A10,2)=LEFT('DB2'!$G$47,2),'DB2'!$F$47)} -> Commissioned Research | C10: =VLOOKUP($A10,'DB1'!$C:$Q,12,0) -> Resilience Assessment of Biodiversity Using Bigdata and Intelligent Technology (RABBIT) (Year 4) | D10: =VLOOKUP($A10,'DB1'!$C:$Q,13,0) -> Choi, Yuyoung | E10: =VLOOKUP($A10,'DB1'!$C:$Q,14,0) -> Environmental Informatics | F10: =VLOOKUP($A10,'DB1'!$C:$Q,15,0) -> Ecology | G10: =VLOOKUP($A10,'DB1'!$C:$Q,9,0) -> 45352 | H10: =VLOOKUP($A10,'DB1'!$C:$Q,10,0) -> 45716
A11: ='DB1'!$C8 -> 2024-039(R) | B11: {=_xlfn.IFS(LEFT($A11,2)='DB2'!$G$43,'DB2'!$F$43,LEFT($A11,2)='DB2'!$G$44,'DB2'!$F$44,LEFT($A11,2)='DB2'!$H$44,'DB2'!$F$44,LEFT($A11,2)='DB2'!$I$44,'DB2'!$F$44,LEFT($A11,2)='DB2'!$J$44,'DB2'!$F$44,LEFT($A11,2)='DB2'!$G$45,'DB2'!$F$45,LEFT($A11,2)='DB2'!$G$46,'DB2'!$F$46,LEFT($A11,2)=LEFT('DB2'!$G$47,2),'DB2'!$F$47)} -> Commissioned Research | C11: =VLOOKUP($A11,'DB1'!$C:$Q,12,0) -> Study on Developing a System for Flood Risk Evaluation and Expected Annual Damage based on Flood Damage Types (Year 2) | D11: =VLOOKUP($A11,'DB1'!$C:$Q,13,0) -> Jung, Kichul | E11: =VLOOKUP($A11,'DB1'!$C:$Q,14,0) -> Water Management | F11: =VLOOKUP($A11,'DB1'!$C:$Q,15,0) -> Environmental Economics | G11: =VLOOKUP($A11,'DB1'!$C:$Q,9,0) -> 45352 | H11: =VLOOKUP($A11,'DB1'!$C:$Q,10,0) -> 45716
A12: ='DB1'!$C9 -> 2024-040 | B12: {=_xlfn.IFS(LEFT($A12,2)='DB2'!$G$43,'DB2'!$F$43,LEFT($A12,2)='DB2'!$G$44,'DB2'!$F$44,LEFT($A12,2)='DB2'!$H$44,'DB2'!$F$44,LEFT($A12,2)='DB2'!$I$44,'DB2'!$F$44,LEFT($A12,2)='DB2'!$J$44,'DB2'!$F$44,LEFT($A12,2)='DB2'!$G$45,'DB2'!$F$45,LEFT($A12,2)='DB2'!$G$46,'DB2'!$F$46,LEFT($A12,2)=LEFT('DB2'!$G$47,2),'DB2'!$F$47)} -> Commissioned Research | C12: =VLOOKUP($A12,'DB1'!$C:$Q,12,0) -> Philippine Climate Resilience Cities Project (KOICA) | D12: =VLOOKUP($A12,'DB1'!$C:$Q,13,0) -> Cho, Hanna | E12: =VLOOKUP($A12,'DB1'!$C:$Q,14,0) -> Climate Adaptation | F12: =VLOOKUP($A12,'DB1'!$C:$Q,15,0) -> International & Regional Collaboration | G12: =VLOOKUP($A12,'DB1'!$C:$Q,9,0) -> 45349 | H12: =VLOOKUP($A12,'DB1'!$C:$Q,10,0) -> 46387
A13: ='DB1'!$C10 -> 2024-043 | B13: {=_xlfn.IFS(LEFT($A13,2)='DB2'!$G$43,'DB2'!$F$43,LEFT($A13,2)='DB2'!$G$44,'DB2'!$F$44,LEFT($A13,2)='DB2'!$H$44,'DB2'!$F$44,LEFT($A13,2)='DB2'!$I$44,'DB2'!$F$44,LEFT($A13,2)='DB2'!$J$44,'DB2'!$F$44,LEFT($A13,2)='DB2'!$G$45,'DB2'!$F$45,LEFT($A13,2)='DB2'!$G$46,'DB2'!$F$46,LEFT($A13,2)=LEFT('DB2'!$G$47,2),'DB2'!$F$47)} -> Commissioned Research | C13: =VLOOKUP($A13,'DB1'!$C:$Q,12,0) -> Developing a National Candidate Site List for Green Restoration (Year 2) | D13: =VLOOKUP($A13,'DB1'!$C:$Q,13,0) -> Son, Seungwoo | E13: =VLOOKUP($A13,'DB1'!$C:$Q,14,0) -> Land Management and Environment | F13: =VLOOKUP($A13,'DB1'!$C:$Q,15,0) -> Ecology | G13: =VLOOKUP($A13,'DB1'!$C:$Q,9,0) -> 45371 | H13: =VLOOKUP($A13,'DB1'!$C:$Q,10,0) -> 45735
A14: ='DB1'!$C11 -> 2024-045 | B14: {=_xlfn.IFS(LEFT($A14,2)='DB2'!$G$43,'DB2'!$F$43,LEFT($A14,2)='DB2'!$G$44,'DB2'!$F$44,LEFT($A14,2)='DB2'!$H$44,'DB2'!$F$44,LEFT($A14,2)='DB2'!$I$44,'DB2'!$F$44,LEFT($A14,2)='DB2'!$J$44,'DB2'!$F$44,LEFT($A14,2)='DB2'!$G$45,'DB2'!$F$45,LEFT($A14,2)='DB2'!$G$46,'DB2'!$F$46,LEFT($A14,2)=LEFT('DB2'!$G$47,2),'DB2'!$F$47)} -> Commissioned Research | C14: =VLOOKUP($A14,'DB1'!$C:$Q,12,0) -> Building an AI-Based Training Dataset for Automatic Wetland Boundary Classification | D14: =VLOOKUP($A14,'DB1'!$C:$Q,13,0) -> Lee, MoungJin | E14: =VLOOKUP($A14,'DB1'!$C:$Q,14,0) -> Environmental Informatics | F14: =VLOOKUP($A14,'DB1'!$C:$Q,15,0) -> Land Management and Environment | G14: =VLOOKUP($A14,'DB1'!$C:$Q,9,0) -> 45372 | H14: =VLOOKUP($A14,'DB1'!$C:$Q,10,0) -> 45671
A15: ='DB1'!$C12 -> 2024-048 | B15: {=_xlfn.IFS(LEFT($A15,2)='DB2'!$G$43,'DB2'!$F$43,LEFT($A15,2)='DB2'!$G$44,'DB2'!$F$44,LEFT($A15,2)='DB2'!$H$44,'DB2'!$F$44,LEFT($A15,2)='DB2'!$I$44,'DB2'!$F$44,LEFT($A15,2)='DB2'!$J$44,'DB2'!$F$44,LEFT($A15,2)='DB2'!$G$45,'DB2'!$F$45,LEFT($A15,2)='DB2'!$G$46,'DB2'!$F$46,LEFT($A15,2)=LEFT('DB2'!$G$47,2),'DB2'!$F$47)} -> Commissioned Research | C15: =VLOOKUP($A15,'DB1'!$C:$Q,12,0) -> Developing Methodologies for Environmental Assessment of Renewable Energy | D15: =VLOOKUP($A15,'DB1'!$C:$Q,13,0) -> Kim, Taeyun | E15: =VLOOKUP($A15,'DB1'!$C:$Q,14,0) -> Environmental Assessment | F15: =VLOOKUP($A15,'DB1'!$C:$Q,15,0) -> Climate Environment (GHG Reduction) | G15: =VLOOKUP($A15,'DB1'!$C:$Q,9,0) -> 45380 | H15: =VLOOKUP($A15,'DB1'!$C:$Q,10,0) -> 45679
A16: ='DB1'!$C13 -> 2024-053 | B16: {=_xlfn.IFS(LEFT($A16,2)='DB2'!$G$43,'DB2'!$F$43,LEFT($A16,2)='DB2'!$G$44,'DB2'!$F$44,LEFT($A16,2)='DB2'!$H$44,'DB2'!$F$44,LEFT($A16,2)='DB2'!$I$44,'DB2'!$F$44,LEFT($A16,2)='DB2'!$J$44,'DB2'!$F$44,LEFT($A16,2)='DB2'!$G$45,'DB2'!$F$45,LEFT($A16,2)='DB2'!$G$46,'DB2'!$F$46,LEFT($A16,2)=LEFT('DB2'!$G$47,2),'DB2'!$F$47)} -> Commissioned Research | C16: =VLOOKUP($A16,'DB1'!$C:$Q,12,0) -> Promoting International Cooperation in the Water Sector (I) | D16: =VLOOKUP($A16,'DB1'!$C:$Q,13,0) -> Kim, Ikjae | E16: =VLOOKUP($A16,'DB1'!$C:$Q,14,0) -> Water Management | F16: =VLOOKUP($A16,'DB1'!$C:$Q,15,0) -> International & Regional Collaboration | G16: =VLOOKUP($A16,'DB1'!$C:$Q,9,0) -> 45399 | H16: =VLOOKUP($A16,'DB1'!$C:$Q,10,0) -> 45698
... A236: ='DB1'!$C233 -> WO2025-06 | B236: {=_xlfn.IFS(LEFT($A236,2)='DB2'!$G$43,'DB2'!$F$43,LEFT($A236,2)='DB2'!$G$44,'DB2'!$F$44,LEFT($A236,2)='DB2'!$H$44,'DB2'!$F$44,LEFT($A236,2)='DB2'!$I$44,'DB2'!$F$44,LEFT($A236,2)='DB2'!$J$44,'DB2'!$F$44,LEFT($A236,2)='DB2'!$G$45,'DB2'!$F$45,LEFT($A236,2)='DB2'!$G$46,'DB2'!$F$46,LEFT($A236,2)=LEFT('DB2'!$G$47,2),'DB2'!$F$47)} -> Policy Issue Study | C236: =VLOOKUP($A236,'DB1'!$C:$Q,12,0) -> Enhancing Community Acceptance of Offshore Wind Power through Public-Private Committee Operations | D236: =VLOOKUP($A236,'DB1'!$C:$Q,13,0) -> Kim, Dokyun | E236: =VLOOKUP($A236,'DB1'!$C:$Q,14,0) -> Socio-Environmental Interface | F236: =VLOOKUP($A236,'DB1'!$C:$Q,15,0) -> Climate Environment (GHG Reduction) | G236: =VLOOKUP($A236,'DB1'!$C:$Q,9,0) -> 45839 | H236: =VLOOKUP($A236,'DB1'!$C:$Q,10,0) -> 46022
A237: ='DB1'!$C234 -> 2025-001 | B237: {=_xlfn.IFS(LEFT($A237,2)='DB2'!$G$43,'DB2'!$F$43,LEFT($A237,2)='DB2'!$G$44,'DB2'!$F$44,LEFT($A237,2)='DB2'!$H$44,'DB2'!$F$44,LEFT($A237,2)='DB2'!$I$44,'DB2'!$F$44,LEFT($A237,2)='DB2'!$J$44,'DB2'!$F$44,LEFT($A237,2)='DB2'!$G$45,'DB2'!$F$45,LEFT($A237,2)='DB2'!$G$46,'DB2'!$F$46,LEFT($A237,2)=LEFT('DB2'!$G$47,2),'DB2'!$F$47)} -> Commissioned Research | D237: =VLOOKUP($A237,'DB1'!$C:$Q,13,0) -> Jung, Huicheul | G237: =VLOOKUP($A237,'DB1'!$C:$Q,9,0) -> 45658 | H237: =VLOOKUP($A237,'DB1'!$C:$Q,10,0) -> 46022
A238: ='DB1'!$C235 -> 2025-009(R) | B238: {=_xlfn.IFS(LEFT($A238,2)='DB2'!$G$43,'DB2'!$F$43,LEFT($A238,2)='DB2'!$G$44,'DB2'!$F$44,LEFT($A238,2)='DB2'!$H$44,'DB2'!$F$44,LEFT($A238,2)='DB2'!$I$44,'DB2'!$F$44,LEFT($A238,2)='DB2'!$J$44,'DB2'!$F$44,LEFT($A238,2)='DB2'!$G$45,'DB2'!$F$45,LEFT($A238,2)='DB2'!$G$46,'DB2'!$F$46,LEFT($A238,2)=LEFT('DB2'!$G$47,2),'DB2'!$F$47)} -> Commissioned Research | C238: =VLOOKUP($A238,'DB1'!$C:$Q,12,0) -> 0 | D238: =VLOOKUP($A238,'DB1'!$C:$Q,13,0) -> Song, Youngil | E238: =VLOOKUP($A238,'DB1'!$C:$Q,14,0) -> 0 | F238: =VLOOKUP($A238,'DB1'!$C:$Q,15,0) -> 0 | G238: =VLOOKUP($A238,'DB1'!$C:$Q,9,0) -> 45658 | H238: =VLOOKUP($A238,'DB1'!$C:$Q,10,0) -> 46022
A239: ='DB1'!$C236 -> 2025-101(R) | B239: {=_xlfn.IFS(LEFT($A239,2)='DB2'!$G$43,'DB2'!$F$43,LEFT($A239,2)='DB2'!$G$44,'DB2'!$F$44,LEFT($A239,2)='DB2'!$H$44,'DB2'!$F$44,LEFT($A239,2)='DB2'!$I$44,'DB2'!$F$44,LEFT($A239,2)='DB2'!$J$44,'DB2'!$F$44,LEFT($A239,2)='DB2'!$G$45,'DB2'!$F$45,LEFT($A239,2)='DB2'!$G$46,'DB2'!$F$46,LEFT($A239,2)=LEFT('DB2'!$G$47,2),'DB2'!$F$47)} -> Commissioned Research | C239: =VLOOKUP($A239,'DB1'!$C:$Q,12,0) -> 0 | D239: =VLOOKUP($A239,'DB1'!$C:$Q,13,0) -> Lee, Seungsoo | E239: =VLOOKUP($A239,'DB1'!$C:$Q,14,0) -> 0 | F239: =VLOOKUP($A239,'DB1'!$C:$Q,15,0) -> 0 | G239: =VLOOKUP($A239,'DB1'!$C:$Q,9,0) -> 45748 | H239: =VLOOKUP($A239,'DB1'!$C:$Q,10,0) -> 46022
A240: ='DB1'!$C237 -> 2025-104 | B240: {=_xlfn.IFS(LEFT($A240,2)='DB2'!$G$43,'DB2'!$F$43,LEFT($A240,2)='DB2'!$G$44,'DB2'!$F$44,LEFT($A240,2)='DB2'!$H$44,'DB2'!$F$44,LEFT($A240,2)='DB2'!$I$44,'DB2'!$F$44,LEFT($A240,2)='DB2'!$J$44,'DB2'!$F$44,LEFT($A240,2)='DB2'!$G$45,'DB2'!$F$45,LEFT($A240,2)='DB2'!$G$46,'DB2'!$F$46,LEFT($A240,2)=LEFT('DB2'!$G$47,2),'DB2'!$F$47)} -> Commissioned Research | C240: =VLOOKUP($A240,'DB1'!$C:$Q,12,0) -> Enhancing Environmental Assessment for Development-Restricted Areas | D240: =VLOOKUP($A240,'DB1'!$C:$Q,13,0) -> Yoon, Jeongho | E240: =VLOOKUP($A240,'DB1'!$C:$Q,14,0) -> Land Management and Environment | F240: =VLOOKUP($A240,'DB1'!$C:$Q,15,0) -> Environmental Assessment | G240: =VLOOKUP($A240,'DB1'!$C:$Q,9,0) -> 45876 | H240: =VLOOKUP($A240,'DB1'!$C:$Q,10,0) -> 46176
A241: ='DB1'!$C238 -> 2025-105(R) | B241: {=_xlfn.IFS(LEFT($A241,2)='DB2'!$G$43,'DB2'!$F$43,LEFT($A241,2)='DB2'!$G$44,'DB2'!$F$44,LEFT($A241,2)='DB2'!$H$44,'DB2'!$F$44,LEFT($A241,2)='DB2'!$I$44,'DB2'!$F$44,LEFT($A241,2)='DB2'!$J$44,'DB2'!$F$44,LEFT($A241,2)='DB2'!$G$45,'DB2'!$F$45,LEFT($A241,2)='DB2'!$G$46,'DB2'!$F$46,LEFT($A241,2)=LEFT('DB2'!$G$47,2),'DB2'!$F$47)} -> Commissioned Research | C241: =VLOOKUP($A241,'DB1'!$C:$Q,12,0) -> Practical Technology Development for Near-Real-Time Biodiversity Monitoring Using AI-Driven Acoustic and Spatial Data Integration | D241: =VLOOKUP($A241,'DB1'!$C:$Q,13,0) -> Choi, Yuyoung | E241: =VLOOKUP($A241,'DB1'!$C:$Q,14,0) -> Ecology | F241: =VLOOKUP($A241,'DB1'!$C:$Q,15,0) -> Environmental Informatics | G241: =VLOOKUP($A241,'DB1'!$C:$Q,9,0) -> 45931 | H241: =VLOOKUP($A241,'DB1'!$C:$Q,10,0) -> 46022
A242: ='DB1'!$C239 -> 2025-106 | B242: {=_xlfn.IFS(LEFT($A242,2)='DB2'!$G$43,'DB2'!$F$43,LEFT($A242,2)='DB2'!$G$44,'DB2'!$F$44,LEFT($A242,2)='DB2'!$H$44,'DB2'!$F$44,LEFT($A242,2)='DB2'!$I$44,'DB2'!$F$44,LEFT($A242,2)='DB2'!$J$44,'DB2'!$F$44,LEFT($A242,2)='DB2'!$G$45,'DB2'!$F$45,LEFT($A242,2)='DB2'!$G$46,'DB2'!$F$46,LEFT($A242,2)=LEFT('DB2'!$G$47,2),'DB2'!$F$47)} -> Commissioned Research | C242: =VLOOKUP($A242,'DB1'!$C:$Q,12,0) -> Pre-Feasibility Assessment and Conceptual Planning for the National Biodiversity Convergence Center | D242: =VLOOKUP($A242,'DB1'!$C:$Q,13,0) -> Lee, Who-Seung | E242: =VLOOKUP($A242,'DB1'!$C:$Q,14,0) -> Ecology | F242: =VLOOKUP($A242,'DB1'!$C:$Q,15,0) -> Environmental Informatics | G242: =VLOOKUP($A242,'DB1'!$C:$Q,9,0) -> 45890 | H242: =VLOOKUP($A242,'DB1'!$C:$Q,10,0) -> 46099
A243: ='DB1'!$C240 -> 2025-107 | B243: {=_xlfn.IFS(LEFT($A243,2)='DB2'!$G$43,'DB2'!$F$43,LEFT($A243,2)='DB2'!$G$44,'DB2'!$F$44,LEFT($A243,2)='DB2'!$H$44,'DB2'!$F$44,LEFT($A243,2)='DB2'!$I$44,'DB2'!$F$44,LEFT($A243,2)='DB2'!$J$44,'DB2'!$F$44,LEFT($A243,2)='DB2'!$G$45,'DB2'!$F$45,LEFT($A243,2)='DB2'!$G$46,'DB2'!$F$46,LEFT($A243,2)=LEFT('DB2'!$G$47,2),'DB2'!$F$47)} -> Commissioned Research | C243: =VLOOKUP($A243,'DB1'!$C:$Q,12,0) -> Development of Measures to Enhance the Climate Change Impact Assessment Framework | D243: =VLOOKUP($A243,'DB1'!$C:$Q,13,0) -> Kim, Yumi | E243: =VLOOKUP($A243,'DB1'!$C:$Q,14,0) -> Environmental Assessment | F243: =VLOOKUP($A243,'DB1'!$C:$Q,15,0) -> Climate Adaptation | G243: =VLOOKUP($A243,'DB1'!$C:$Q,9,0) -> 45898 | H243: =VLOOKUP($A243,'DB1'!$C:$Q,10,0) -> 46262
A244: ='DB1'!$C241 -> 2025-108 | B244: {=_xlfn.IFS(LEFT($A244,2)='DB2'!$G$43,'DB2'!$F$43,LEFT($A244,2)='DB2'!$G$44,'DB2'!$F$44,LEFT($A244,2)='DB2'!$H$44,'DB2'!$F$44,LEFT($A244,2)='DB2'!$I$44,'DB2'!$F$44,LEFT($A244,2)='DB2'!$J$44,'DB2'!$F$44,LEFT($A244,2)='DB2'!$G$45,'DB2'!$F$45,LEFT($A244,2)='DB2'!$G$46,'DB2'!$F$46,LEFT($A244,2)=LEFT('DB2'!$G$47,2),'DB2'!$F$47)} -> Commissioned Research | C244: =VLOOKUP($A244,'DB1'!$C:$Q,12,0) -> Korea’s Practice of Addressing Air Pollution and GHG Emissions from Small- and Medium-scale Industries | D244: =VLOOKUP($A244,'DB1'!$C:$Q,13,0) -> Chang, Hoon | E244: =VLOOKUP($A244,'DB1'!$C:$Q,14,0) -> Atmospheric Environment | F244: =VLOOKUP($A244,'DB1'!$C:$Q,15,0) -> Climate Environment (GHG Reduction) | G244: =VLOOKUP($A244,'DB1'!$C:$Q,9,0) -> 45901 | H244: =VLOOKUP($A244,'DB1'!$C:$Q,10,0) -> 46476
A245: ='DB1'!$C242 -> 2025-109 | B245: {=_xlfn.IFS(LEFT($A245,2)='DB2'!$G$43,'DB2'!$F$43,LEFT($A245,2)='DB2'!$G$44,'DB2'!$F$44,LEFT($A245,2)='DB2'!$H$44,'DB2'!$F$44,LEFT($A245,2)='DB2'!$I$44,'DB2'!$F$44,LEFT($A245,2)='DB2'!$J$44,'DB2'!$F$44,LEFT($A245,2)='DB2'!$G$45,'DB2'!$F$45,LEFT($A245,2)='DB2'!$G$46,'DB2'!$F$46,LEFT($A245,2)=LEFT('DB2'!$G$47,2),'DB2'!$F$47)} -> Commissioned Research | C245: =VLOOKUP($A245,'DB1'!$C:$Q,12,0) -> Development of a Response Framework for the Carbon Border Adjustment Mechanism | D245: =VLOOKUP($A245,'DB1'!$C:$Q,13,0) -> Kim, Sungjin | E245: =VLOOKUP($A245,'DB1'!$C:$Q,14,0) -> Climate Environment (GHG Reduction) | F245: =VLOOKUP($A245,'DB1'!$C:$Q,15,0) -> Environmental Economics | G245: =VLOOKUP($A245,'DB1'!$C:$Q,9,0) -> 45924 | H245: =VLOOKUP($A245,'DB1'!$C:$Q,10,0) -> 46288
A246: ='DB1'!$C243 -> 2025-110 | B246: {=_xlfn.IFS(LEFT($A246,2)='DB2'!$G$43,'DB2'!$F$43,LEFT($A246,2)='DB2'!$G$44,'DB2'!$F$44,LEFT($A246,2)='DB2'!$H$44,'DB2'!$F$44,LEFT($A246,2)='DB2'!$I$44,'DB2'!$F$44,LEFT($A246,2)='DB2'!$J$44,'DB2'!$F$44,LEFT($A246,2)='DB2'!$G$45,'DB2'!$F$45,LEFT($A246,2)='DB2'!$G$46,'DB2'!$F$46,LEFT($A246,2)=LEFT('DB2'!$G$47,2),'DB2'!$F$47)} -> Commissioned Research | C246: =VLOOKUP($A246,'DB1'!$C:$Q,12,0) -> Enhancement of the Electric Vehicle Subsidy System and Development of Support Measures Tailored for Each Vehicle Type | D246: =VLOOKUP($A246,'DB1'!$C:$Q,13,0) -> Lee, Jeongeun | E246: =VLOOKUP($A246,'DB1'!$C:$Q,14,0) -> Climate Environment (GHG Reduction) | F246: =VLOOKUP($A246,'DB1'!$C:$Q,15,0) -> Environmental Economics | G246: =VLOOKUP($A246,'DB1'!$C:$Q,9,0) -> 45924 | H246: =VLOOKUP($A246,'DB1'!$C:$Q,10,0) -> 46133
A247: ='DB1'!$C244 -> 2025-111 | B247: {=_xlfn.IFS(LEFT($A247,2)='DB2'!$G$43,'DB2'!$F$43,LEFT($A247,2)='DB2'!$G$44,'DB2'!$F$44,LEFT($A247,2)='DB2'!$H$44,'DB2'!$F$44,LEFT($A247,2)='DB2'!$I$44,'DB2'!$F$44,LEFT($A247,2)='DB2'!$J$44,'DB2'!$F$44,LEFT($A247,2)='DB2'!$G$45,'DB2'!$F$45,LEFT($A247,2)='DB2'!$G$46,'DB2'!$F$46,LEFT($A247,2)=LEFT('DB2'!$G$47,2),'DB2'!$F$47)} -> Commissioned Research | C247: =VLOOKUP($A247,'DB1'!$C:$Q,12,0) -> Development of Biodiversity Subsidy Management Measures in Response to the Global Biodiversity Framework | D247: =VLOOKUP($A247,'DB1'!$C:$Q,13,0) -> Koo, Kyung Ah | E247: =VLOOKUP($A247,'DB1'!$C:$Q,14,0) -> Ecology | F247: =VLOOKUP($A247,'DB1'!$C:$Q,15,0) -> Environmental Economics | G247: =VLOOKUP($A247,'DB1'!$C:$Q,9,0) -> 45925 | H247: =VLOOKUP($A247,'DB1'!$C:$Q,10,0) -> 46289
A248: ='DB1'!$C245 -> 2025-112 | B248: {=_xlfn.IFS(LEFT($A248,2)='DB2'!$G$43,'DB2'!$F$43,LEFT($A248,2)='DB2'!$G$44,'DB2'!$F$44,LEFT($A248,2)='DB2'!$H$44,'DB2'!$F$44,LEFT($A248,2)='DB2'!$I$44,'DB2'!$F$44,LEFT($A248,2)='DB2'!$J$44,'DB2'!$F$44,LEFT($A248,2)='DB2'!$G$45,'DB2'!$F$45,LEFT($A248,2)='DB2'!$G$46,'DB2'!$F$46,LEFT($A248,2)=LEFT('DB2'!$G$47,2),'DB2'!$F$47)} -> Commissioned Research | C248: =VLOOKUP($A248,'DB1'!$C:$Q,12,0) -> Analysis of Implementation Trends and Development of Response Measures for the CBD Kunming-Montreal Global Biodiversity Framework (III) | D248: =VLOOKUP($A248,'DB1'!$C:$Q,13,0) -> Lee, Who-Seung | E248: =VLOOKUP($A248,'DB1'!$C:$Q,14,0) -> Ecology | F248: =VLOOKUP($A248,'DB1'!$C:$Q,15,0) -> International & Regional Collaboration | G248: =VLOOKUP($A248,'DB1'!$C:$Q,9,0) -> 45925 | H248: =VLOOKUP($A248,'DB1'!$C:$Q,10,0) -> 46104
A249: ='DB1'!$C246 -> 2025-113 | B249: {=_xlfn.IFS(LEFT($A249,2)='DB2'!$G$43,'DB2'!$F$43,LEFT($A249,2)='DB2'!$G$44,'DB2'!$F$44,LEFT($A249,2)='DB2'!$H$44,'DB2'!$F$44,LEFT($A249,2)='DB2'!$I$44,'DB2'!$F$44,LEFT($A249,2)='DB2'!$J$44,'DB2'!$F$44,LEFT($A249,2)='DB2'!$G$45,'DB2'!$F$45,LEFT($A249,2)='DB2'!$G$46,'DB2'!$F$46,LEFT($A249,2)=LEFT('DB2'!$G$47,2),'DB2'!$F$47)} -> Commissioned Research | C249: =VLOOKUP($A249,'DB1'!$C:$Q,12,0) -> Development of Measures to Improve the Agency Contract System and Operations for Enhancing the Reliability of the Environmental Impact Assessment System | D249: =VLOOKUP($A249,'DB1'!$C:$Q,13,0) -> Yi, Youngjae | E249: =VLOOKUP($A249,'DB1'!$C:$Q,14,0) -> Environmental Assessment | F249: =VLOOKUP($A249,'DB1'!$C:$Q,15,0) -> Environmental Economics | G249: =VLOOKUP($A249,'DB1'!$C:$Q,9,0) -> 45943 | H249: =VLOOKUP($A249,'DB1'!$C:$Q,10,0) -> 46182
... A301: ='DB1'!$C298 -> WO2025-11-01 | B301: {=_xlfn.IFS(LEFT($A301,2)='DB2'!$G$43,'DB2'!$F$43,LEFT($A301,2)='DB2'!$G$44,'DB2'!$F$44,LEFT($A301,2)='DB2'!$H$44,'DB2'!$F$44,LEFT($A301,2)='DB2'!$I$44,'DB2'!$F$44,LEFT($A301,2)='DB2'!$J$44,'DB2'!$F$44,LEFT($A301,2)='DB2'!$G$45,'DB2'!$F$45,LEFT($A301,2)='DB2'!$G$46,'DB2'!$F$46,LEFT($A301,2)=LEFT('DB2'!$G$47,2),'DB2'!$F$47)} -> Policy Issue Study | C301: =VLOOKUP($A301,'DB1'!$C:$Q,12,0) -> Assessment of Effectiveness and Policy Measures for Securing River Flood Buffer Spaces | D301: =VLOOKUP($A301,'DB1'!$C:$Q,13,0) -> Choi, Mikyoung | E301: =VLOOKUP($A301,'DB1'!$C:$Q,14,0) -> Water Management | F301: =VLOOKUP($A301,'DB1'!$C:$Q,15,0) -> Land Management and Environment | G301: =VLOOKUP($A301,'DB1'!$C:$Q,9,0) -> 45971 | H301: =VLOOKUP($A301,'DB1'!$C:$Q,10,0) -> 46022
A302: ='DB1'!$C299 -> 0
A303: ='DB1'!$C300 -> 0
A304: ='DB1'!$C301 -> 0
A305: ='DB1'!$C302 -> 0
A306: ='DB1'!$C303 -> 0
A307: ='DB1'!$C304 -> 0
A308: ='DB1'!$C305 -> 0
A309: ='DB1'!$C306 -> 0
A310: ='DB1'!$C307 -> 0
A311: ='DB1'!$C308 -> 0

Sheet DB1
A1: No | B1: 과제구분 | C1: 과제번호▲ | D1: 과제명 | E1: 주제어 | F1: 책임자사번코드 | G1: 책임자 | H1: 부서코드 | I1: 연구부서 | J1: 연구원 예산 | K1: 연구시작일 | L1: 연구종료일 | M1: 발주처 | N1: 과제명(영문) | O1: PI | P1: Primary Focus | Q1: Secondary Focus | R1: 실(영문) | S1: 본부(영문)
A2: 1 | B2: 수탁과제 | C2: 2023-066 | D2: 단양 유네스코 세계지질공원 지정 추진 용역 | F2: 50018 | G2: 이수재 | H2: 201902192 | I2: 자연환경연구실 | J2: 174545450 | K2: 45054 | L2: 45713 | M2: 단양군청 | N2: Supporting Danyang’s Bid for UNESCO Global Geopark Status | O2: =IFERROR(VLOOKUP($G2,'DB2'!$A:$B,2,0),"공동과책 확인") -> Lee, Soojae | P2: Ecology | Q2: Land Management and Environment | R2: =IFERROR(VLOOKUP($I2,'DB2'!$F$2:$I$50,2,0),"옛날 부서명 확인") -> Natural Environment Division | S2: =IFERROR(VLOOKUP($I2,'DB2'!$F$2:$I$50,4,0),"옛날 부서명 확인") -> Land and Environment Research Group
A3: 2 | B3: 수탁과제 | C3: 2023-067 | D3: 백령대청 유네스코 세계지질공원 인증 추진 용역 | F3: 50018 | G3: 이수재 | H3: 202508192 | I3: 자연환경연구실 | J3: 449090900 | K3: 45056 | L3: 46275 | M3: 인천광역시 | N3: Supporting Baengnyeong–Daecheong’s Bid for UNESCO Global Geopark Status | O3: =IFERROR(VLOOKUP($G3,'DB2'!$A:$B,2,0),"공동과책 확인") -> Lee, Soojae | P3: Ecology | Q3: Land management and environment | R3: =IFERROR(VLOOKUP($I3,'DB2'!$F$2:$I$50,2,0),"옛날 부서명 확인") -> Natural Environment Division | S3: =IFERROR(VLOOKUP($I3,'DB2'!$F$2:$I$50,4,0),"옛날 부서명 확인") -> Land and Environment Research Group
A4: 3 | B4: 수탁과제 | C4: 2023-111 | D4: 군산시 해상풍력 주민수용성 확보 및 이해관계자 역량 강화 용역 | F4: 10155 | G4: 조공장 | H4: 202508189 | I4: 생활환경사회연구실 | J4: 621000000 | K4: 45287 | L4: 45961 | M4: 군산시청 | N4: Consulting Service for Promoting Community Acceptance of Offshore Wind Power and Strengthening Stakeholder Capacities in Gunsan | O4: =IFERROR(VLOOKUP($G4,'DB2'!$A:$B,2,0),"공동과책 확인") -> Cho, Kongjang | P4: Socio-Environmental Interface | Q4: Climate Environment (GHG Reduction) | R4: =IFERROR(VLOOKUP($I4,'DB2'!$F$2:$I$50,2,0),"옛날 부서명 확인") -> Living Environment and Society Division | S4: =IFERROR(VLOOKUP($I4,'DB2'!$F$2:$I$50,4,0),"옛날 부서명 확인") -> Sustainable Development Research Group
A5: 4 | B5: 수탁과제 | C5: 2024-020 | D5: 과학 기반 자연환경복원 전과정 관리방안 연구 | F5: 10282 | G5: 손승우 | H5: 201902191 | I5: 국토관리연구실 | J5: 136170000 | K5: 45309 | L5: 45673 | M5: 환경부 | N5: A Study on Science-Based Approaches to Full-Cycle Management of Environmental Restoration | O5: =IFERROR(VLOOKUP($G5,'DB2'!$A:$B,2,0),"공동과책 확인") -> Son, Seungwoo | P5: Land Management and Environment | Q5: Ecology | R5: =IFERROR(VLOOKUP($I5,'DB2'!$F$2:$I$50,2,0),"옛날 부서명 확인") -> Spatial Planning and Management Division | S5: =IFERROR(VLOOKUP($I5,'DB2'!$F$2:$I$50,4,0),"옛날 부서명 확인") -> Land and Environment Research Group
A6: 5 | B6: 수탁과제 | C6: 2024-032 | D6: 아프리카돼지열병(ASF) 차단울타리 효과 분석 및 관리 개선방안 연구 | F6: 10300 | G6: 구경아 | H6: 201902192 | I6: 자연환경연구실 | J6: 86363630 | K6: 45390 | L6: 45815 | M6: 환경부 | N6: A Study on the Effectiveness of African Swine Fever (ASF) Fencing and Strategies for Improved Management | O6: =IFERROR(VLOOKUP($G6,'DB2'!$A:$B,2,0),"공동과책 확인") -> Koo, Kyung Ah | P6: Environmental Health | Q6: Ecology | R6: =IFERROR(VLOOKUP($I6,'DB2'!$F$2:$I$50,2,0),"옛날 부서명 확인") -> Natural Environment Division | S6: =IFERROR(VLOOKUP($I6,'DB2'!$F$2:$I$50,4,0),"옛날 부서명 확인") -> Land and Environment Research Group
A7: 6 | B7: 수탁과제 | C7: 2024-036(R) | D7: 딥러닝 기반 생물다양성 예측 및 리질리언스 평가 기술 개발(4차년도) | F7: 10346 | G7: 최유영 | H7: 201902164 | I7: 국토전략평가실 | J7: 107955000 | K7: 45352 | L7: 45716 | M7: 한국연구재단 | N7: Resilience Assessment of Biodiversity Using Bigdata and Intelligent Technology (RABBIT) (Year 4) | O7: =IFERROR(VLOOKUP($G7,'DB2'!$A:$B,2,0),"공동과책 확인") -> Choi, Yuyoung | P7: Environmental Informatics | Q7: Ecology | R7: =IFERROR(VLOOKUP($I7,'DB2'!$F$2:$I$50,2,0),"옛날 부서명 확인") -> Land Strategy Assessment Division | S7: =IFERROR(VLOOKUP($I7,'DB2'!$F$2:$I$50,4,0),"옛날 부서명 확인") -> Environmental Assessment Group
A8: 7 | B8: 수탁과제 | C8: 2024-039(R) | D8: 홍수피해 유형화 기반 취약지역 평가 및 피해액 추정 모형 개발 연구(2차년도) | F8: 10333 | G8: 정기철 | H8: 201902175 | I8: 물관리연구실 | J8: 80415000 | K8: 45352 | L8: 45716 | M8: 한국연구재단 | N8: Study on Developing a System for Flood Risk Evaluation and Expected Annual Damage based on Flood Damage Types (Year 2) | O8: =IFERROR(VLOOKUP($G8,'DB2'!$A:$B,2,0),"공동과책 확인") -> Jung, Kichul | P8: Water Management | Q8: Environmental Economics | R8: =IFERROR(VLOOKUP($I8,'DB2'!$F$2:$I$50,2,0),"옛날 부서명 확인") -> Water Management Division | S8: =IFERROR(VLOOKUP($I8,'DB2'!$F$2:$I$50,4,0),"옛날 부서명 확인") -> Land and Environment Research Group
A9: 8 | B9: 수탁과제 | C9: 2024-040 | D9: 필리핀 도시 기후회복력 역량강화 사업 PMC 용역 | F9: 10166 | G9: 조한나 | H9: 202508123 | I9: 기후적응협력실 | J9: 458068280 | K9: 45349 | L9: 46387 | M9: 한국국제협력단 | N9: Philippine Climate Resilience Cities Project (KOICA) | O9: =IFERROR(VLOOKUP($G9,'DB2'!$A:$B,2,0),"공동과책 확인") -> Cho, Hanna | P9: Climate Adaptation | Q9: International & Regional Collaboration | R9: =IFERROR(VLOOKUP($I9,'DB2'!$F$2:$I$50,2,0),"옛날 부서명 확인") -> Climate Adaptation Cooperation Division | S9: =IFERROR(VLOOKUP($I9,'DB2'!$F$2:$I$50,4,0),"옛날 부서명 확인") -> Korea Adaptation Center for Climate Change
A10: 9 | B10: 수탁과제 | C10: 2024-043 | D10: 국토환경 녹색복원 후보목록 2차년도 조사연구 | F10: 10282 | G10: 손승우 | H10: 201902191 | I10: 국토관리연구실 | J10: 180000000 | K10: 45371 | L10: 45735 | M10: 환경부 | N10: Developing a National Candidate Site List for Green Restoration (Year 2) | O10: =IFERROR(VLOOKUP($G10,'DB2'!$A:$B,2,0),"공동과책 확인") -> Son, Seungwoo | P10: Land Management and Environment | Q10: Ecology | R10: =IFERROR(VLOOKUP($I10,'DB2'!$F$2:$I$50,2,0),"옛날 부서명 확인") -> Spatial Planning and Management Division | S10: =IFERROR(VLOOKUP($I10,'DB2'!$F$2:$I$50,4,0),"옛날 부서명 확인") -> Land and Environment Research Group
A11: 10 | B11: 수탁과제 | C11: 2024-045 | D11: AI기반 습지경계 자동분류 학습데이터 구축 | F11: 10162 | G11: 이명진 | H11: 201902191 | I11: 국토관리연구실 | J11: 38863630 | K11: 45372 | L11: 45671 | M11: 환경부 | N11: Building an AI-Based Training Dataset for Automatic Wetland Boundary Classification | O11: =IFERROR(VLOOKUP($G11,'DB2'!$A:$B,2,0),"공동과책 확인") -> Lee, MoungJin | P11: Environmental Informatics | Q11: Land Management and Environment | R11: =IFERROR(VLOOKUP($I11,'DB2'!$F$2:$I$50,2,0),"옛날 부서명 확인") -> Spatial Planning and Management Division | S11: =IFERROR(VLOOKUP($I11,'DB2'!$F$2:$I$50,4,0),"옛날 부서명 확인") -> Land and Environment Research Group
A12: 11 | B12: 수탁과제 | C12: 2024-048 | D12: 신재생에너지 환경성평가 방안 연구 | F12: 10227 | G12: 김태윤 | H12: 201902165 | I12: 기후에너지평가실 | J12: 170000000 | K12: 45380 | L12: 45679 | M12: 환경부 환경영향평가과 | N12: Developing Methodologies for Environmental Assessment of Renewable Energy | O12: =IFERROR(VLOOKUP($G12,'DB2'!$A:$B,2,0),"공동과책 확인") -> Kim, Taeyun | P12: Environmental Assessment | Q12: Climate Environment (GHG Reduction) | R12: =IFERROR(VLOOKUP($I12,'DB2'!$F$2:$I$50,2,0),"옛날 부서명 확인") -> Climate and Energy Assessment Division | S12: =IFERROR(VLOOKUP($I12,'DB2'!$F$2:$I$50,4,0),"옛날 부서명 확인") -> Environmental Assessment Group
A13: 12 | B13: 수탁과제 | C13: 2024-053 | D13: 물분야 국제협력 활성화 연구(Ⅰ) | F13: 10184 | G13: 김익재 | H13: 201902190 | I13: 물관리연구실 | J13: 90000000 | K13: 45399 | L13: 45698 | M13: 환경부 | N13: Promoting International Cooperation in the Water Sector (I) | O13: =IFERROR(VLOOKUP($G13,'DB2'!$A:$B,2,0),"공동과책 확인") -> Kim, Ikjae | P13: Water Management | Q13: International & Regional Collaboration | R13: =IFERROR(VLOOKUP($I13,'DB2'!$F$2:$I$50,2,0),"옛날 부서명 확인") -> Water Management Division | S13: =IFERROR(VLOOKUP($I13,'DB2'!$F$2:$I$50,4,0),"옛날 부서명 확인") -> Land and Environment Research Group
A14: 13 | B14: 수탁과제 | C14: 2024-054 | D14: 2024년 환경관련 조세 및 세입계정 통계 작성 | F14: 10228 | G14: 강성원 | H14: 201902200 | I14: 녹색경제연구실 | J14: 86363630 | K14: 45400 | L14: 45669 | M14: 환경부 | N14: Compilation of 2024 Environmental Tax and Revenue Account Statistics | O14: =IFERROR(VLOOKUP($G14,'DB2'!$A:$B,2,0),"공동과책 확인") -> Kang, Sungwon | P14: Environmental Economics | R14: =IFERROR(VLOOKUP($I14,'DB2'!$F$2:$I$50,2,0),"옛날 부서명 확인") -> Green Economy Division | S14: =IFERROR(VLOOKUP($I14,'DB2'!$F$2:$I$50,4,0),"옛날 부서명 확인") -> Climate and Atmospheric Strategy Research Group
A15: 14 | B15: 수탁과제 | C15: 2024-055 | D15: 익산왕궁 자연환경복원사업 기본계획 및 예비타당성조사 대응방안 연구용역 | F15: 10282 | G15: 손승우 | H15: 201902191 | I15: 국토관리연구실 | J15: 95950000 | K15: 45408 | L15: 45772 | M15: 전북특별자치도 | N15: Developing Response Strategies for Framework Plan and Feasibility Assessment in Environmental Restoration of Wanggung-ri, Iksan | O15: =IFERROR(VLOOKUP($G15,'DB2'!$A:$B,2,0),"공동과책 확인") -> Son, Seungwoo | P15: Land Management and Environment | Q15: Ecology | R15: =IFERROR(VLOOKUP($I15,'DB2'!$F$2:$I$50,2,0),"옛날 부서명 확인") -> Spatial Planning and Management Division | S15: =IFERROR(VLOOKUP($I15,'DB2'!$F$2:$I$50,4,0),"옛날 부서명 확인") -> Land and Environment Research Group
A16: 15 | B16: 수탁과제 | C16: 2024-056 | D16: 국가검진자료-대기노출량 연계빅데이터를 활용한 질병발생영향분석 및 연구용 DATA 공개 | F16: 10228 | G16: 강성원 | H16: 201902200 | I16: 녹색경제연구실 | J16: 191545450 | K16: 45383 | L16: 45777 | M16: 질병관리청 국립보건연구원 | N16: Analysis of Disease Incidence Using Big Data Linking National Health Screening Records and Air Pollution Exposure, and Release of Research Data | O16: =IFERROR(VLOOKUP($G16,'DB2'!$A:$B,2,0),"공동과책 확인") -> Kang, Sungwon | P16: Environmental Health | Q16: Atmospheric Environment | R16: =IFERROR(VLOOKUP($I16,'DB2'!$F$2:$I$50,2,0),"옛날 부서명 확인") -> Green Economy Division | S16: =IFERROR(VLOOKUP($I16,'DB2'!$F$2:$I$50,4,0),"옛날 부서명 확인") -> Climate and Atmospheric Strategy Research Group
A17: 16 | B17: 수탁과제 | C17: 2024-061 | D17: 환경분야 국제개발협력사업 관련 규정 제개정안 마련 연구 | F17: 10185 | G17: 명수정 | H17: 201902192 | I17: 자연환경연구실 | J17: 50500000 | K17: 45413 | L17: 45714 | M17: 환경부 | N17: Preparing Regulatory Revisions for Environmental International Development Cooperation Projects | O17: =IFERROR(VLOOKUP($G17,'DB2'!$A:$B,2,0),"공동과책 확인") -> Myeong, Soojeong | P17: International & Regional Collaboration | R17: =IFERROR(VLOOKUP($I17,'DB2'!$F$2:$I$50,2,0),"옛날 부서명 확인") -> Natural Environment Division | S17: =IFERROR(VLOOKUP($I17,'DB2'!$F$2:$I$50,4,0),"옛날 부서명 확인") -> Land and Environment Research Group
A18: 17 | B18: 수탁과제 | C18: 2024-062 | D18: 2023년 기준 환경보호지출계정 편제 | F18: 10139 | G18: 김종호 | H18: 201902200 | I18: 순환경제연구실 | J18: 136363630 | K18: 45415 | L18: 45747 | M18: 환경부 녹색기술개발과 | N18: Compilation of Environmental Protection Expenditure Accounts for 2023 | O18: =IFERROR(VLOOKUP($G18,'DB2'!$A:$B,2,0),"공동과책 확인") -> Kim, Jongho | P18: Environmental Economics | Q18: Environmental Informatics | R18: =IFERROR(VLOOKUP($I18,'DB2'!$F$2:$I$50,2,0),"옛날 부서명 확인") -> Circular Economy Division | S18: =IFERROR(VLOOKUP($I18,'DB2'!$F$2:$I$50,4,0),"옛날 부서명 확인") -> Sustainable Development Research Group
A19: 18 | B19: 수탁과제 | C19: 2024-068 | D19: 탄소중립 기술정보 종합 및 활용기반 구축 -에너지 부문(전환·산업·수송·건물) | F19: 10327 | G19: 김성진 | H19: 201902197 | I19: 탄소중립연구실 | J19: 80181810 | K19: 45441 | L19: 45738 | M19: 환경부 온실가스종합정보센터 | N19: Developing a Comprehensive Database and Utilization Framework for Carbon Neutrality Technologies in the Energy Sector (Transition, Industry, Transport, and Buildings) | O19: =IFERROR(VLOOKUP($G19,'DB2'!$A:$B,2,0),"공동과책 확인") -> Kim, Sungjin | P19: Climate Environment (GHG Reduction) | Q19: Environmental Informatics | R19: =IFERROR(VLOOKUP($I19,'DB2'!$F$2:$I$50,2,0),"옛날 부서명 확인") -> Carbon Neutrality Division | S19: =IFERROR(VLOOKUP($I19,'DB2'!$F$2:$I$50,4,0),"옛날 부서명 확인") -> Climate and Atmospheric Strategy Research Group
A20: 19 | B20: 수탁과제 | C20: 2024-071 | D20: 이차전지 산업폐수의 공공폐수처리시설 적정 처리방안 연구 | F20: 10189 | G20: 한대호 | H20: 201902190 | I20: 물관리연구실 | J20: 86418180 | K20: 45446 | L20: 45716 | M20: 한국환경공단 | N20: Developing Appropriate Treatment Methods for Public Wastewater Facilities Handling Industrial Wastewater from Secondary Battery Production | O20: =IFERROR(VLOOKUP($G20,'DB2'!$A:$B,2,0),"공동과책 확인") -> Han, Daeho | P20: Water Management | Q20: Circular Economy | R20: =IFERROR(VLOOKUP($I20,'DB2'!$F$2:$I$50,2,0),"옛날 부서명 확인") -> Water Management Division | S20: =IFERROR(VLOOKUP($I20,'DB2'!$F$2:$I$50,4,0),"옛날 부서명 확인") -> Land and Environment Research Group
A21: 20 | B21: 수탁과제 | C21: 2024-072 | D21: 도시의 개발사업 등 관련 환경영향평가 개선방안 마련 연구 | F21: 10249 | G21: 이영재 | H21: 201902163 | I21: 국토전략평가실 | J21: 39750000 | K21: 45447 | L21: 45716 | M21: 환경부 국토환경정책과 | N21: Developing Strategies to Improve Environmental Impact Assessments for Urban Development Projects | O21: =IFERROR(VLOOKUP($G21,'DB2'!$A:$B,2,0),"공동과책 확인") -> Yi, Youngjae | P21: Environmental Assessment | Q21: Land Management and Environment | R21: =IFERROR(VLOOKUP($I21,'DB2'!$F$2:$I$50,2,0),"옛날 부서명 확인") -> Land Strategy Assessment Division | S21: =IFERROR(VLOOKUP($I21,'DB2'!$F$2:$I$50,4,0),"옛날 부서명 확인") -> Environmental Assessment Group
A22: 21 | B22: 수탁과제 | C22: 2024-074 | D22: 산업폐수관리 개선방안 마련 연구 | F22: 10189 | G22: 한대호 | H22: 201902190 | I22: 물관리연구실 | J22: 81818180 | K22: 45456 | L22: 45807 | M22: 환경부 | N22: Developing Strategies to Improve Industrial Wastewater Management | O22: =IFERROR(VLOOKUP($G22,'DB2'!$A:$B,2,0),"공동과책 확인") -> Han, Daeho | P22: Water Management | Q22: Environmental Health | R22: =IFERROR(VLOOKUP($I22,'DB2'!$F$2:$I$50,2,0),"옛날 부서명 확인") -> Water Management Division | S22: =IFERROR(VLOOKUP($I22,'DB2'!$F$2:$I$50,4,0),"옛날 부서명 확인") -> Land and Environment Research Group
A23: 22 | B23: 수탁과제 | C23: 2024-075 | D23: 2024년 녹색화학 협의체 운영 등 기반구축 사업 | F23: 10236 | G23: 서양원 | H23: 201902119 | I23: 지속가능발전연구본부 | J23: 150054000 | K23: 45456 | L23: 45747 | M23: 환경부 화학물질정책과 | N23: 2024 Capacity-Building, Including Operation of the Green Chemistry Council | O23: =IFERROR(VLOOKUP($G23,'DB2'!$A:$B,2,0),"공동과책 확인") -> Suh, Yang-won | P23: Environmental Health | Q23: Climate Adaptation | R23: =IFERROR(VLOOKUP($I23,'DB2'!$F$2:$I$50,2,0),"옛날 부서명 확인") -> Sustainable Development Research Group | S23: =IFERROR(VLOOKUP($I23,'DB2'!$F$2:$I$50,4,0),"옛날 부서명 확인") -> Sustainable Development Research Group
A24: 23 | B24: 수탁과제 | C24: 2024-080 | D24: 2025년도 전기차 차종별 보조금 지급체계 개편 연구 | F24: 10344 | G24: 이정은 | H24: 201902197 | I24: 탄소중립연구실 | J24: 59363430 | K24: 45488 | L24: 45730 | M24: 환경부 대기미래전략과 | N24: Research on Reforming the 2025 Subsidy Scheme for Electric Vehicles | O24: =IFERROR(VLOOKUP($G24,'DB2'!$A:$B,2,0),"공동과책 확인") -> Lee, Jeongeun | P24: Climate Environment (GHG Reduction) | Q24: Environmental Economics | R24: =IFERROR(VLOOKUP($I24,'DB2'!$F$2:$I$50,2,0),"옛날 부서명 확인") -> Carbon Neutrality Division | S24: =IFERROR(VLOOKUP($I24,'DB2'!$F$2:$I$50,4,0),"옛날 부서명 확인") -> Climate and Atmospheric Strategy Research Group
A25: 24 | B25: 수탁과제 | C25: 2024-081 | D25: 환경관리 고도화를 위한 환경정책 발전방안 연구 | F25: 10132 | G25: 박창석 | H25: 201902191 | I25: 임원실 | J25: 69280000 | K25: 45488 | L25: 45747 | M25: 환경부 | N25: Advancing Environmental Policies for Enhanced Environmental Management | O25: =IFERROR(VLOOKUP($G25,'DB2'!$A:$B,2,0),"공동과책 확인") -> Park, Chang Sug | P25: Land Management and Environment | Q25: Socio-Environmental Interface | R25: =IFERROR(VLOOKUP($I25,'DB2'!$F$2:$I$50,2,0),"옛날 부서명 확인") -> Executive Office | S25: =IFERROR(VLOOKUP($I25,'DB2'!$F$2:$I$50,4,0),"옛날 부서명 확인") -> Executive Office
A26: 25 | B26: 수탁과제 | C26: 2024-082 | D26: 한국형 탄소중립도시 지정 및 제도 마련 연구 | F26: 10132 | G26: 박창석 | H26: 201902191 | I26: 임원실 | J26: 79025000 | K26: 45488 | L26: 45747 | M26: 환경부 녹색전환정책과 | N26: Study on the Designation and Institutional Development for K-Carbon Neutral Cities | O26: =IFERROR(VLOOKUP($G26,'DB2'!$A:$B,2,0),"공동과책 확인") -> Park, Chang Sug | P26: Climate Environment (GHG Reduction) | Q26: Land Management and Environment | R26: =IFERROR(VLOOKUP($I26,'DB2'!$F$2:$I$50,2,0),"옛날 부서명 확인") -> Executive Office | S26: =IFERROR(VLOOKUP($I26,'DB2'!$F$2:$I$50,4,0),"옛날 부서명 확인") -> Executive Office
A27: 26 | B27: 수탁과제 | C27: 2024-084 | D27: 소록도 자연가치 등의 보전ㆍ활용을 위한 마스터플랜 수립 연구 | F27: 10282 | G27: 손승우 | H27: 201902191 | I27: 국토관리연구실 | J27: 72270000 | K27: 45495 | L27: 45734 | M27: 환경부 | N27: Developing a Master Plan for Conserving and Utilizing the Natural Value of Sorokdo | O27: =IFERROR(VLOOKUP($G27,'DB2'!$A:$B,2,0),"공동과책 확인") -> Son, Seungwoo | P27: Land Management and Environment | Q27: Ecology | R27: =IFERROR(VLOOKUP($I27,'DB2'!$F$2:$I$50,2,0),"옛날 부서명 확인") -> Spatial Planning and Management Division | S27: =IFERROR(VLOOKUP($I27,'DB2'!$F$2:$I$50,4,0),"옛날 부서명 확인") -> Land and Environment Research Group
A28: 27 | B28: 수탁과제 | C28: 2024-085 | D28: 세계 생물다양성 프레임워크 이행을 위한 유전자 다양성 국가지표(안) 마련(1차년도) | F28: 10300 | G28: 구경아 | H28: 201902192 | I28: 자연환경연구실 | J28: 68100000 | K28: 45502 | L28: 45744 | M28: 국립생물자원관 | N28: Developing National Indicators for Genetic Diversity to Support Implementation of the Global Biodiversity Framework (Year 1) | O28: =IFERROR(VLOOKUP($G28,'DB2'!$A:$B,2,0),"공동과책 확인") -> Koo, Kyung Ah | P28: Ecology | Q28: International & Regional Collaboration | R28: =IFERROR(VLOOKUP($I28,'DB2'!$F$2:$I$50,2,0),"옛날 부서명 확인") -> Natural Environment Division | S28: =IFERROR(VLOOKUP($I28,'DB2'!$F$2:$I$50,4,0),"옛날 부서명 확인") -> Land and Environment Research Group
A29: 28 | B29: 수탁과제 | C29: 2024-086 | D29: 수자원위성 활용기술 개발(Ⅱ)(1차) | F29: 10162 | G29: 이명진 | H29: 201902191 | I29: 국토관리연구실 | J29: 80589750 | K29: 45498 | L29: 45672 | M29: K-water 연구원 | N29: Developing Technologies for Water Resources Satellite Utilization (II) (Phase 1) | O29: =IFERROR(VLOOKUP($G29,'DB2'!$A:$B,2,0),"공동과책 확인") -> Lee, MoungJin | P29: Water Management | Q29: Environmental Informatics | R29: =IFERROR(VLOOKUP($I29,'DB2'!$F$2:$I$50,2,0),"옛날 부서명 확인") -> Spatial Planning and Management Division | S29: =IFERROR(VLOOKUP($I29,'DB2'!$F$2:$I$50,4,0),"옛날 부서명 확인") -> Land and Environment Research Group
... A32: 31 | B32: 수탁과제 | C32: 2024-089 | D32: 생물다양성협약 쿤밍-몬트리올 GBF 이행동향 분석 및 대응 방안 연구(II) | F32: 10300 | G32: 구경아 | H32: 201902192 | I32: 자연환경연구실 | J32: 69500000 | K32: 45516 | L32: 45754 | M32: 환경부 | N32: Trends in the Implementation of the CBD Kunming-Montreal Global Biodiversity Framework and Development of Response Strategies (II) | O32: =IFERROR(VLOOKUP($G32,'DB2'!$A:$B,2,0),"공동과책 확인") -> Koo, Kyung Ah | P32: Ecology | Q32: International & Regional Collaboration | R32: =IFERROR(VLOOKUP($I32,'DB2'!$F$2:$I$50,2,0),"옛날 부서명 확인") -> Natural Environment Division | S32: =IFERROR(VLOOKUP($I32,'DB2'!$F$2:$I$50,4,0),"옛날 부서명 확인") -> Land and Environment Research Group
A33: 32 | B33: 수탁과제 | C33: 2024-090 | D33: 배출허용기준 관리 개선방안 마련 연구 | F33: 50021 | G33: 공성용 | H33: 201902187 | I33: 대기환경연구실 | J33: 78400000 | K33: 45527 | L33: 45679 | M33: 국립환경과학원 | N33: Developing Strategies to Improve Emission Standard Management | O33: =IFERROR(VLOOKUP($G33,'DB2'!$A:$B,2,0),"공동과책 확인") -> Gong, Sungyong | P33: Atmospheric Environment | R33: =IFERROR(VLOOKUP($I33,'DB2'!$F$2:$I$50,2,0),"옛날 부서명 확인") -> Atmospheric Environment Division | S33: =IFERROR(VLOOKUP($I33,'DB2'!$F$2:$I$50,4,0),"옛날 부서명 확인") -> Climate and Atmospheric Strategy Research Group
A34: 33 | B34: 수탁과제 | C34: 2024-091 | D34: 제2차 물 재이용 기본계획 타당성 검토 및 변경 수립 연구 | F34: 10318 | G34: 이문환 | H34: 202508190 | I34: 물관리연구실 | J34: 302181810 | K34: 45538 | L34: 45988 | M34: 환경부 | N34: Feasibility Review and Preparation of Draft Amendments for the Second Water Reuse Master Plan | O34: =IFERROR(VLOOKUP($G34,'DB2'!$A:$B,2,0),"공동과책 확인") -> Lee, Moonhwan | P34: Water Management | R34: =IFERROR(VLOOKUP($I34,'DB2'!$F$2:$I$50,2,0),"옛날 부서명 확인") -> Water Management Division | S34: =IFERROR(VLOOKUP($I34,'DB2'!$F$2:$I$50,4,0),"옛날 부서명 확인") -> Land and Environment Research Group
A35: 34 | B35: 수탁과제 | C35: 2024-093 | D35: 제5차 국가환경종합계획(2020-2040) 수정계획 수립 연구(I) | F35: 10132 | G35: 박창석 | H35: 201902191 | I35: 임원실 | J35: 151263000 | K35: 45555 | L35: 45734 | M35: 환경부 | N35: Developing a Revision Plan for the 5th Comprehensive National Environmental Plan (2020–2040) (I) | O35: =IFERROR(VLOOKUP($G35,'DB2'!$A:$B,2,0),"공동과책 확인") -> Park, Chang Sug | P35: Land Management and Environment | R35: =IFERROR(VLOOKUP($I35,'DB2'!$F$2:$I$50,2,0),"옛날 부서명 확인") -> Executive Office | S35: =IFERROR(VLOOKUP($I35,'DB2'!$F$2:$I$50,4,0),"옛날 부서명 확인") -> Executive Office
A36: 35 | B36: 수탁과제 | C36: 2024-094 | D36: 탄소중립을 위한 개발사업의 탄소총량제 도입방안 연구 | F36: 10084 | G36: 윤정호,손승우 | H36: 202508205 | I36: 국토관리연구실 | J36: 99000000 | K36: 45558 | L36: 45891 | M36: 재단법인 경기연구원 | N36: Implementing a Carbon Cap System in Development Projects for Carbon Neutrality | O36: =IFERROR(VLOOKUP($G36,'DB2'!$A:$B,2,0),"공동과책 확인") -> 공동과책 확인 | P36: Climate Environment (GHG Reduction) | Q36: Environmental Economics | R36: =IFERROR(VLOOKUP($I36,'DB2'!$F$2:$I$50,2,0),"옛날 부서명 확인") -> Spatial Planning and Management Division | S36: =IFERROR(VLOOKUP($I36,'DB2'!$F$2:$I$50,4,0),"옛날 부서명 확인") -> Land and Environment Research Group
A37: 36 | B37: 수탁과제 | C37: 2024-096 | D37: 제1차 국가물관리기본계획 타당성 검토 및 변경계획안 마련 연구(I) | F37: 10203 | G37: 한혜진 | H37: 202508190 | I37: 물관리연구실 | J37: 171000000 | K37: 45583 | L37: 45947 | M37: 환경부 | N37: Feasibility Review and Preparation of Draft Amendments for the First Master Plan for National Water Management (I) | O37: =IFERROR(VLOOKUP($G37,'DB2'!$A:$B,2,0),"공동과책 확인") -> Han, Haejin | P37: Water Management | R37: =IFERROR(VLOOKUP($I37,'DB2'!$F$2:$I$50,2,0),"옛날 부서명 확인") -> Water Management Division | S37: =IFERROR(VLOOKUP($I37,'DB2'!$F$2:$I$50,4,0),"옛날 부서명 확인") -> Land and Environment Research Group
A38: 37 | B38: 수탁과제 | C38: 2024-097 | D38: 제3차 국가 물환경관리기본계획 수립 | F38: 10214 | G38: 김호정 | H38: 202508190 | I38: 물관리연구실 | J38: 180000000 | K38: 45587 | L38: 46008 | M38: 환경부 물환경정책과 | N38: Developing the Third Master Plan for National Water Environment Management | O38: =IFERROR(VLOOKUP($G38,'DB2'!$A:$B,2,0),"공동과책 확인") -> Kim, Hojeong | P38: Water Management | R38: =IFERROR(VLOOKUP($I38,'DB2'!$F$2:$I$50,2,0),"옛날 부서명 확인") -> Water Management Division | S38: =IFERROR(VLOOKUP($I38,'DB2'!$F$2:$I$50,4,0),"옛날 부서명 확인") -> Land and Environment Research Group
A39: 38 | B39: 수탁과제 | C39: 2024-098 | D39: 실내환경관리센터 발전방안 마련 연구 | F39: 10297 | G39: 정다운 | H39: 201902119 | I39: 환경보건연구실 | J39: 45200000 | K39: 45590 | L39: 45739 | M39: 환경부 생활환경과 | N39: Developing a Strategic Roadmap for the Advancement of Indoor Environment Management Center | O39: =IFERROR(VLOOKUP($G39,'DB2'!$A:$B,2,0),"공동과책 확인") -> Jung, Dawoon | P39: Environmental Health | R39: =IFERROR(VLOOKUP($I39,'DB2'!$F$2:$I$50,2,0),"옛날 부서명 확인") -> Environmental Health Division | S39: =IFERROR(VLOOKUP($I39,'DB2'!$F$2:$I$50,4,0),"옛날 부서명 확인") -> Sustainable Development Research Group
A40: 39 | B40: 수탁과제 | C40: 2024-099(R) | D40: 2차 미세플라스틱 환경오염 문제해결을 위한 융합솔루션 개발(5차년도) | F40: 10065 | G40: 박정규 | H40: 201902119 | I40: 환경보건연구실 | J40: 30000000 | K40: 45514 | L40: 45878 | M40: 안전성평가연구소 | N40: Research on Convergent Approaches to Mitigate Secondary Microplastic Pollution (Year 5) | O40: =IFERROR(VLOOKUP($G40,'DB2'!$A:$B,2,0),"공동과책 확인") -> Park, Jeonggue | P40: Environmental Health | Q40: Marine Environment | R40: =IFERROR(VLOOKUP($I40,'DB2'!$F$2:$I$50,2,0),"옛날 부서명 확인") -> Environmental Health Division | S40: =IFERROR(VLOOKUP($I40,'DB2'!$F$2:$I$50,4,0),"옛날 부서명 확인") -> Sustainable Development Research Group
A41: 40 | B41: 수탁과제 | C41: 2024-100 | D41: 생태계서비스 활성화 촉진을 위한 구역(지역)화 추진방안 마련 연구 | F41: 10186 | G41: 최희선 | H41: 202508205 | I41: 국토관리연구실 | J41: 99000000 | K41: 45601 | L41: 45898 | M41: 환경부 | N41: Developing Strategies to Implement Zoning for Enhancing Ecosystem Services | O41: =IFERROR(VLOOKUP($G41,'DB2'!$A:$B,2,0),"공동과책 확인") -> Choi, Hee-Sun | P41: Land Management and Environment | Q41: Ecology | R41: =IFERROR(VLOOKUP($I41,'DB2'!$F$2:$I$50,2,0),"옛날 부서명 확인") -> Spatial Planning and Management Division | S41: =IFERROR(VLOOKUP($I41,'DB2'!$F$2:$I$50,4,0),"옛날 부서명 확인") -> Land and Environment Research Group
A42: 41 | B42: 수탁과제 | C42: 2024-101 | D42: 석탄화력발전소 주변지역 환경보건평가-종합평가 | F42: 10211 | G42: 배현주 | H42: 202508119 | I42: 환경보건연구실 | J42: 98000000 | K42: 45600 | L42: 45965 | M42: 국립환경과학원 | N42: Comprehensive Environmental Health Assessment of Regions Around Coal-Fired Power Plants | O42: =IFERROR(VLOOKUP($G42,'DB2'!$A:$B,2,0),"공동과책 확인") -> Bae, Hyun-Joo | P42: Environmental Health | Q42: Atmospheric Environment | R42: =IFERROR(VLOOKUP($I42,'DB2'!$F$2:$I$50,2,0),"옛날 부서명 확인") -> Environmental Health Division | S42: =IFERROR(VLOOKUP($I42,'DB2'!$F$2:$I$50,4,0),"옛날 부서명 확인") -> Sustainable Development Research Group
A43: 42 | B43: 수탁과제 | C43: 2024-102 | D43: 차등화된 환경영향평가체계 마련 연구(1차) | F43: 10290 | G43: 양경 | H43: 201902165 | I43: 기후에너지평가실 | J43: 20000000 | K43: 45609 | L43: 45698 | M43: 환경부 | N43: Developing a Tiered Environmental Impact Assessment System (Phase 1) | O43: =IFERROR(VLOOKUP($G43,'DB2'!$A:$B,2,0),"공동과책 확인") -> Yang, Kyung | P43: Environmental Assessment | R43: =IFERROR(VLOOKUP($I43,'DB2'!$F$2:$I$50,2,0),"옛날 부서명 확인") -> Climate and Energy Assessment Division | S43: =IFERROR(VLOOKUP($I43,'DB2'!$F$2:$I$50,4,0),"옛날 부서명 확인") -> Environmental Assessment Group
A44: 43 | B44: 수탁과제 | C44: 2024-103 | D44: 유독물질 지정관리체계 개편을 위한 취급시설 기준 및 규정수량 규제영향분석 연구 | F44: 10191 | G44: 신상철 | H44: 202508204 | I44: 순환경제연구실 | J44: 175454540 | K44: 45618 | L44: 45961 | M44: 화학물질안전원 | N44: Impact Analysis of Handling Facility Standards and Quantity Limits for Reforming the Hazardous Substance Designation and Management System | O44: =IFERROR(VLOOKUP($G44,'DB2'!$A:$B,2,0),"공동과책 확인") -> Shin, Sang-Cheol | P44: Environmental Health | R44: =IFERROR(VLOOKUP($I44,'DB2'!$F$2:$I$50,2,0),"옛날 부서명 확인") -> Circular Economy Division | S44: =IFERROR(VLOOKUP($I44,'DB2'!$F$2:$I$50,4,0),"옛날 부서명 확인") -> Sustainable Development Research Group
A45: 44 | B45: 수탁과제 | C45: 2024-104 | D45: 아태지역의 플라스틱 오염 문제 해결을 위한 국가 전략 및 계획 분석(Analysis of National Strategies and Plans for Addressing Plastic Pollution in the Asia-Pacific Region) | F45: 10273 | G45: 이소라 | H45: 202508204 | I45: 순환경제연구실 | J45: 135714150 | K45: 45625 | L45: 45930 | M45: UNEP | N45: Analysis of National Strategies and Plans for Addressing Plastic Pollution in the Asia-Pacific Region | O45: =IFERROR(VLOOKUP($G45,'DB2'!$A:$B,2,0),"공동과책 확인") -> Yi, Sora | P45: Circular Economy | Q45: International & Regional Collaboration | R45: =IFERROR(VLOOKUP($I45,'DB2'!$F$2:$I$50,2,0),"옛날 부서명 확인") -> Circular Economy Division | S45: =IFERROR(VLOOKUP($I45,'DB2'!$F$2:$I$50,4,0),"옛날 부서명 확인") -> Sustainable Development Research Group
A46: 45 | B46: 수탁과제 | C46: 2024-105 | D46: 국가 온실가스 장기 감축경로 마련을 위한 연구 | F46: 10327 | G46: 김성진 | H46: 201902197 | I46: 탄소중립연구실 | J46: 45454540 | K46: 45625 | L46: 45684 | M46: 환경부 기후전략과 | N46: Developing National Long-Term Greenhouse Gas Reduction Pathways | O46: =IFERROR(VLOOKUP($G46,'DB2'!$A:$B,2,0),"공동과책 확인") -> Kim, Sungjin | P46: Climate Environment (GHG Reduction) | R46: =IFERROR(VLOOKUP($I46,'DB2'!$F$2:$I$50,2,0),"옛날 부서명 확인") -> Carbon Neutrality Division | S46: =IFERROR(VLOOKUP($I46,'DB2'!$F$2:$I$50,4,0),"옛날 부서명 확인") -> Climate and Atmospheric Strategy Research Group
A47: 46 | B47: 수탁과제 | C47: 2024-106 | D47: 통합환경관리 대상업종 확대 검토 | F47: 10189 | G47: 한대호 | H47: 201902190 | I47: 물관리연구실 | J47: 90909090 | K47: 45630 | L47: 45869 | M47: 환경부 | N47: Study on Expanding the Scope of Industries Subject to Integrated Environmental Management | O47: =IFERROR(VLOOKUP($G47,'DB2'!$A:$B,2,0),"공동과책 확인") -> Han, Daeho | P47: Socio-Environmental Interface | Q47: Land management and environment | R47: =IFERROR(VLOOKUP($I47,'DB2'!$F$2:$I$50,2,0),"옛날 부서명 확인") -> Water Management Division | S47: =IFERROR(VLOOKUP($I47,'DB2'!$F$2:$I$50,4,0),"옛날 부서명 확인") -> Land and Environment Research Group
A48: 47 | B48: 수탁과제 | C48: 2024-107 | D48: 상수원 관리 고도화를 위한 환경관리기술 적용 분석 | F48: 10319 | G48: 전동진 | H48: 201902190 | I48: 물관리연구실 | J48: 44180000 | K48: 45632 | L48: 45751 | M48: 환경부 | N48: Study on the Application of Environmental Management Technologies for Advanced Water Source Management | O48: =IFERROR(VLOOKUP($G48,'DB2'!$A:$B,2,0),"공동과책 확인") -> Jeon, Dongjin | P48: Water Management | Q48: Environmental Informatics | R48: =IFERROR(VLOOKUP($I48,'DB2'!$F$2:$I$50,2,0),"옛날 부서명 확인") -> Water Management Division | S48: =IFERROR(VLOOKUP($I48,'DB2'!$F$2:$I$50,4,0),"옛날 부서명 확인") -> Land and Environment Research Group
A49: 48 | B49: 수탁과제 | C49: 2024-108 | D49: 수도사업 체계 정교화를 위한 수도법 정비방안 연구 | F49: 10254 | G49: 류재나 | H49: 202508190 | I49: 물관리연구실 | J49: 89200000 | K49: 45635 | L49: 45904 | M49: 환경부 | N49: Study on Reforming the Water Supply and Waterworks Installation Act to Refine the Water Supply System | O49: =IFERROR(VLOOKUP($G49,'DB2'!$A:$B,2,0),"공동과책 확인") -> Ryu, Jaena | P49: Water Management | R49: =IFERROR(VLOOKUP($I49,'DB2'!$F$2:$I$50,2,0),"옛날 부서명 확인") -> Water Management Division | S49: =IFERROR(VLOOKUP($I49,'DB2'!$F$2:$I$50,4,0),"옛날 부서명 확인") -> Land and Environment Research Group
A50: 49 | B50: 수탁과제 | C50: 2024-109 | D50: 수도용 자재와 제품에 대한 인증제도 개선방안 마련 연구 | F50: 10254 | G50: 류재나 | H50: 202508190 | I50: 물관리연구실 | J50: 81000000 | K50: 45636 | L50: 45995 | M50: 환경부 | N50: Developing Strategies to Improve the Certification System for Water Supply Materials and Products | O50: =IFERROR(VLOOKUP($G50,'DB2'!$A:$B,2,0),"공동과책 확인") -> Ryu, Jaena | P50: Water Management | R50: =IFERROR(VLOOKUP($I50,'DB2'!$F$2:$I$50,2,0),"옛날 부서명 확인") -> Water Management Division | S50: =IFERROR(VLOOKUP($I50,'DB2'!$F$2:$I$50,4,0),"옛날 부서명 확인") -> Land and Environment Research Group
A51: 50 | B51: 수탁과제 | C51: 2024-110 | D51: 지속가능발전 국가기본전략(26-45) 수립 | F51: 10220 | G51: 정우현 | H51: 202508189 | I51: 생활환경사회연구실 | J51: 124727270 | K51: 45644 | L51: 45961 | M51: 국무조정실 | N51: Establishment of the National Basic Strategy for Sustainable Development (2026-2045) | O51: =IFERROR(VLOOKUP($G51,'DB2'!$A:$B,2,0),"공동과책 확인") -> Chung, Woo Hyun | P51: Socio-Environmental Interface | R51: =IFERROR(VLOOKUP($I51,'DB2'!$F$2:$I$50,2,0),"옛날 부서명 확인") -> Living Environment and Society Division | S51: =IFERROR(VLOOKUP($I51,'DB2'!$F$2:$I$50,4,0),"옛날 부서명 확인") -> Sustainable Development Research Group
A52: 52 | B52: 수탁과제 | C52: 2025-001-01 | D52: 국가 기후위기 적응대책 수립 및 주류화 지원 | F52: 10158 | G52: 신지영 | H52: 202508124 | I52: 성과관리팀 | J52: 640000000 | K52: 45658 | L52: 46022 | M52: 환경부 기후적응과 | N52: Formulating and Mainstreaming National Climate Crisis Adaptation Measures | O52: =IFERROR(VLOOKUP($G52,'DB2'!$A:$B,2,0),"공동과책 확인") -> Shin, Jiyoung | P52: Climate Adaptation | R52: =IFERROR(VLOOKUP($I52,'DB2'!$F$2:$I$50,2,0),"옛날 부서명 확인") -> Performance Management Team | S52: =IFERROR(VLOOKUP($I52,'DB2'!$F$2:$I$50,4,0),"옛날 부서명 확인") -> Department of Planning and Strategy
A53: 53 | B53: 수탁과제 | C53: 2025-001-02 | D53: 지자체 기후 적응 및 취약성 개선 | F53: 10323 | G53: 박진한 | H53: 202508124 | I53: 기후적응정책실 | J53: 980000000 | K53: 45658 | L53: 46022 | M53: 환경부 기후적응과 | N53: Enhancing Climate Adaptation and Reducing Vulnerability in Local Governments | O53: =IFERROR(VLOOKUP($G53,'DB2'!$A:$B,2,0),"공동과책 확인") -> Park, Jin-han | P53: Climate Adaptation | Q53: Socio-Environmental Interface | R53: =IFERROR(VLOOKUP($I53,'DB2'!$F$2:$I$50,2,0),"옛날 부서명 확인") -> Climate Adaptation Policy Division | S53: =IFERROR(VLOOKUP($I53,'DB2'!$F$2:$I$50,4,0),"옛날 부서명 확인") -> Korea Adaptation Center for Climate Change
A54: 54 | B54: 수탁과제 | C54: 2025-001-03 | D54: 적응 주체별 적응역량 강화 | F54: 10166 | G54: 조한나 | H54: 202508123 | I54: 기후적응협력실 | J54: 640000000 | K54: 45658 | L54: 46022 | M54: 환경부 기후적응과 | N54: Capacity Building for Different Adaptation Stakeholders | O54: =IFERROR(VLOOKUP($G54,'DB2'!$A:$B,2,0),"공동과책 확인") -> Cho, Hanna | P54: Climate Adaptation | R54: =IFERROR(VLOOKUP($I54,'DB2'!$F$2:$I$50,2,0),"옛날 부서명 확인") -> Climate Adaptation Cooperation Division | S54: =IFERROR(VLOOKUP($I54,'DB2'!$F$2:$I$50,4,0),"옛날 부서명 확인") -> Korea Adaptation Center for Climate Change
A55: 55 | B55: 수탁과제 | C55: 2025-001-04 | D55: 국내외 적응 협력 및 확산 | F55: 10166 | G55: 조한나 | H55: 202508123 | I55: 기후적응정책실 | J55: 670000000 | K55: 45658 | L55: 46022 | M55: 환경부 기후적응과 | N55: Promoting Climate Adaptation Cooperation in Korea and Abroad | O55: =IFERROR(VLOOKUP($G55,'DB2'!$A:$B,2,0),"공동과책 확인") -> Cho, Hanna | P55: Climate Adaptation | Q55: International & Regional Collaboration | R55: =IFERROR(VLOOKUP($I55,'DB2'!$F$2:$I$50,2,0),"옛날 부서명 확인") -> Climate Adaptation Policy Division | S55: =IFERROR(VLOOKUP($I55,'DB2'!$F$2:$I$50,4,0),"옛날 부서명 확인") -> Korea Adaptation Center for Climate Change
A56: 56 | B56: 수탁과제 | C56: 2025-001-05 | D56: 총괄 및 적응정책 연구 | F56: 10210 | G56: 정휘철 | H56: 202508168 | I56: 국가기후위기적응센터 | J56: 165000000 | K56: 45658 | L56: 46022 | M56: 환경부 기후적응과 | N56: Comprehensive Study and Research on Adaptation Policies | O56: =IFERROR(VLOOKUP($G56,'DB2'!$A:$B,2,0),"공동과책 확인") -> Jung, Huicheul | P56: Climate Adaptation | R56: =IFERROR(VLOOKUP($I56,'DB2'!$F$2:$I$50,2,0),"옛날 부서명 확인") -> Korea Adaptation Center for Climate Change | S56: =IFERROR(VLOOKUP($I56,'DB2'!$F$2:$I$50,4,0),"옛날 부서명 확인") -> Korea Adaptation Center for Climate Change
A57: 57 | B57: 수탁과제 | C57: 2025-002 | D57: DM 프로젝트(3차년도) | F57: 10317 | G57: 이승수 | H57: 202508190 | I57: 물관리연구실 | J57: 301550000 | K57: 45658 | L57: 46022 | M57: 미래과학아카데미 | N57: DM Project (Year 3) | O57: =IFERROR(VLOOKUP($G57,'DB2'!$A:$B,2,0),"공동과책 확인") -> Lee, Seungsoo | P57: Water Management | R57: =IFERROR(VLOOKUP($I57,'DB2'!$F$2:$I$50,2,0),"옛날 부서명 확인") -> Water Management Division | S57: =IFERROR(VLOOKUP($I57,'DB2'!$F$2:$I$50,4,0),"옛날 부서명 확인") -> Land and Environment Research Group
A58: 58 | B58: 수탁과제 | C58: 2025-003 | D58: 2025년 국토환경성평가지도 구축·운영 사업 | F58: 10084 | G58: 윤정호 | H58: 202508205 | I58: 국토관리연구실 | J58: 2196000000 | K58: 45658 | L58: 46022 | M58: 환경부 국토환경정책과 | N58: 2025 Development and Management of National Land Environmental Assessment Maps | O58: =IFERROR(VLOOKUP($G58,'DB2'!$A:$B,2,0),"공동과책 확인") -> Yoon, Jeongho | P58: Land Management and Environment | Q58: Environmental Assessment | R58: =IFERROR(VLOOKUP($I58,'DB2'!$F$2:$I$50,2,0),"옛날 부서명 확인") -> Spatial Planning and Management Division | S58: =IFERROR(VLOOKUP($I58,'DB2'!$F$2:$I$50,4,0),"옛날 부서명 확인") -> Land and Environment Research Group
A59: 59 | B59: 수탁과제 | C59: 2025-004 | D59: KOICA 기후주류화 전략 및 액션플랜 수립을 위한 컨설팅 용역(2차) | F59: 10252 | G59: 장훈 | H59: 202508199 | I59: 기후대기전략연구본부 | J59: 199967501 | K59: 45658 | L59: 46022 | M59: 한국국제협력단 | N59: KOICA Climate Mainstreaming Strategy and Action Plan Development Consulting (Phase 2) | O59: =IFERROR(VLOOKUP($G59,'DB2'!$A:$B,2,0),"공동과책 확인") -> Chang, Hoon | P59: Climate Adaptation | Q59: International & Regional Collaboration | R59: =IFERROR(VLOOKUP($I59,'DB2'!$F$2:$I$50,2,0),"옛날 부서명 확인") -> Climate and Atmospheric Strategy Research Group | S59: =IFERROR(VLOOKUP($I59,'DB2'!$F$2:$I$50,4,0),"옛날 부서명 확인") -> Climate and Atmospheric Strategy Research Group
A60: 60 | B60: 수탁과제 | C60: 2025-005(R) | D60: 습지생태계 서비스 및 가치평가 정량화 기술개발(4차년도) | F60: 10292 | G60: 김현노 | H60: 202508095 | I60: 녹색경제연구실 | J60: 249984000 | K60: 45658 | L60: 46022 | M60: 한국환경산업기술원 | N60: Developing Quantitative Assessment Techniques for Wetland Ecosystem Services and Value (Year 4) | O60: =IFERROR(VLOOKUP($G60,'DB2'!$A:$B,2,0),"공동과책 확인") -> Kim, Hyunno | P60: Environmental Economics | Q60: Ecology | R60: =IFERROR(VLOOKUP($I60,'DB2'!$F$2:$I$50,2,0),"옛날 부서명 확인") -> Green Economy Division | S60: =IFERROR(VLOOKUP($I60,'DB2'!$F$2:$I$50,4,0),"옛날 부서명 확인") -> Climate and Atmospheric Strategy Research Group
A61: 61 | B61: 수탁과제 | C61: 2025-006(R) | D61: 공공주도 해상풍력 적합입지 발굴 연구(2차년도) | F61: 10155 | G61: 조공장 | H61: 202508189 | I61: 생활환경사회연구실 | J61: 450000000 | K61: 45658 | L61: 46022 | M61: 한국에너지공단 | N61: Identifying Suitable Sites for Public-Led Offshore Wind Projects (Year 2) | O61: =IFERROR(VLOOKUP($G61,'DB2'!$A:$B,2,0),"공동과책 확인") -> Cho, Kongjang | P61: Socio-Environmental Interface | Q61: Climate Environment (GHG Reduction) | R61: =IFERROR(VLOOKUP($I61,'DB2'!$F$2:$I$50,2,0),"옛날 부서명 확인") -> Living Environment and Society Division | S61: =IFERROR(VLOOKUP($I61,'DB2'!$F$2:$I$50,4,0),"옛날 부서명 확인") -> Sustainable Development Research Group
A62: 62 | B62: 수탁과제 | C62: 2025-007(R) | D62: WMO IG³IS 이행사업 개선(2차년도) | F62: 10348 | G62: 한지현,심창섭 | H62: 202508187 | I62: 대기환경연구실 | J62: 130000000 | K62: 45658 | L62: 46022 | M62: 한국기상산업기술원 | N62: Enhancing the Implementation of WMO’s Integrated Global Greenhouse Gas Information System (IG³IS) (Year 2) | O62: =IFERROR(VLOOKUP($G62,'DB2'!$A:$B,2,0),"공동과책 확인") -> 공동과책 확인 | P62: Environmental Informatics | Q62: Climate Environment (GHG Reduction) | R62: =IFERROR(VLOOKUP($I62,'DB2'!$F$2:$I$50,2,0),"옛날 부서명 확인") -> Atmospheric Environment Division | S62: =IFERROR(VLOOKUP($I62,'DB2'!$F$2:$I$50,4,0),"옛날 부서명 확인") -> Climate and Atmospheric Strategy Research Group
A63: 63 | B63: 수탁과제 | C63: 2025-008(R) | D63: AI 기반 해양수색구조 의사결정지원시스템 개발(4차년도) | F63: 10257 | G63: 김충기 | H63: 202508192 | I63: 자연환경연구실 | J63: 1181000000 | K63: 45658 | L63: 46022 | M63: 해양수산과학기술진흥원 | N63: Development of an AI-Based Decision Support System for Maritime Search and Rescue (Year 4) | O63: =IFERROR(VLOOKUP($G63,'DB2'!$A:$B,2,0),"공동과책 확인") -> Kim, Choong-ki | P63: Marine Environment | Q63: Environmental Informatics | R63: =IFERROR(VLOOKUP($I63,'DB2'!$F$2:$I$50,2,0),"옛날 부서명 확인") -> Natural Environment Division | S63: =IFERROR(VLOOKUP($I63,'DB2'!$F$2:$I$50,4,0),"옛날 부서명 확인") -> Land and Environment Research Group
A64: 65 | B64: 수탁과제 | C64: 2025-009(R)-01 | D64: 의사결정 지원을 위한 적응대책 선정 및 리스크 저감효과 진단 모듈 개발 | F64: 50026 | G64: 송영일 | H64: 202508124 | I64: 기후적응정책실 | J64: 558000000 | K64: 45658 | L64: 46022 | M64: 한국환경산업기술원 | N64: Developing a Decision-Support Module for Adaptation Strategy Selection and Risk Mitigation Evaluation | O64: =IFERROR(VLOOKUP($G64,'DB2'!$A:$B,2,0),"공동과책 확인") -> Song, Youngil | P64: Climate Adaptation | Q64: Environmental Informatics | R64: =IFERROR(VLOOKUP($I64,'DB2'!$F$2:$I$50,2,0),"옛날 부서명 확인") -> Climate Adaptation Policy Division | S64: =IFERROR(VLOOKUP($I64,'DB2'!$F$2:$I$50,4,0),"옛날 부서명 확인") -> Korea Adaptation Center for Climate Change
A65: 66 | B65: 수탁과제 | C65: 2025-009(R)-02 | D65: 지역기반 물관리 기후변화 영향 및 리스크 평가 시스템 개발 | F65: 10193 | G65: 안종호 | H65: 202508190 | I65: 물관리연구실 | J65: 40400000 | K65: 45658 | L65: 46022 | M65: 한국환경산업기술원 | N65: Developing a Regional Water Management System for Climate Change Impact and Risk Evaluation | O65: =IFERROR(VLOOKUP($G65,'DB2'!$A:$B,2,0),"공동과책 확인") -> Ahn, Jongho | P65: Water Management | Q65: Climate Adaptation | R65: =IFERROR(VLOOKUP($I65,'DB2'!$F$2:$I$50,2,0),"옛날 부서명 확인") -> Water Management Division | S65: =IFERROR(VLOOKUP($I65,'DB2'!$F$2:$I$50,4,0),"옛날 부서명 확인") -> Land and Environment Research Group
A66: 67 | B66: 수탁과제 | C66: 2025-010(R) | D66: 탄소중립 이행을 위한 글로벌 전력부문 모형 개발(4차년도) | F66: 10252 | G66: 장훈 | H66: 202508199 | I66: 기후대기전략연구본부 | J66: 280700000 | K66: 45658 | L66: 46022 | M66: 한국환경산업기술원 | N66: Global Power Sector Modeling for Advancing Carbon Neutrality (Year 4) | O66: =IFERROR(VLOOKUP($G66,'DB2'!$A:$B,2,0),"공동과책 확인") -> Chang, Hoon | P66: Climate Environment (GHG Reduction) | Q66: International & Regional Collaboration | R66: =IFERROR(VLOOKUP($I66,'DB2'!$F$2:$I$50,2,0),"옛날 부서명 확인") -> Climate and Atmospheric Strategy Research Group | S66: =IFERROR(VLOOKUP($I66,'DB2'!$F$2:$I$50,4,0),"옛날 부서명 확인") -> Climate and Atmospheric Strategy Research Group
A67: 68 | B67: 수탁과제 | C67: 2025-011(R) | D67: 도시공간 기후탄력성 확보 기술 평가 및 의사결정지원 시스템 개발(4차년도) | F67: 10210 | G67: 정휘철 | H67: 202508168 | I67: 국가기후위기적응센터 | J67: 299000000 | K67: 45658 | L67: 46022 | M67: 한국환경산업기술원 | N67: Evaluation of Urban Climate Resilience Technologies and Development of a Decision Support System (Year 4) | O67: =IFERROR(VLOOKUP($G67,'DB2'!$A:$B,2,0),"공동과책 확인") -> Jung, Huicheul | P67: Climate Adaptation | Q67: Environmental Informatics | R67: =IFERROR(VLOOKUP($I67,'DB2'!$F$2:$I$50,2,0),"옛날 부서명 확인") -> Korea Adaptation Center for Climate Change | S67: =IFERROR(VLOOKUP($I67,'DB2'!$F$2:$I$50,4,0),"옛날 부서명 확인") -> Korea Adaptation Center for Climate Change
A68: 69 | B68: 수탁과제 | C68: 2025-012(R) | D68: 생활화학제품 함유 혼합물 대상 인체 복합 유해성 평가용 AOP기반 통합시험평가접근법(ITS/IATA) 개발(3차년도) | F68: 10297 | G68: 정다운 | H68: 202508119 | I68: 환경보건연구실 | J68: 150000000 | K68: 45658 | L68: 46022 | M68: 한국환경산업기술원 | N68: Developing an AOP-Based Integrated Testing and Assessment Approach (ITS/IATA) for Complex Human Toxicity Evaluation of Mixtures in Consumer Chemical Products (Year 3) | O68: =IFERROR(VLOOKUP($G68,'DB2'!$A:$B,2,0),"공동과책 확인") -> Jung, Dawoon | P68: Environmental Health | R68: =IFERROR(VLOOKUP($I68,'DB2'!$F$2:$I$50,2,0),"옛날 부서명 확인") -> Environmental Health Division | S68: =IFERROR(VLOOKUP($I68,'DB2'!$F$2:$I$50,4,0),"옛날 부서명 확인") -> Sustainable Development Research Group
A69: 70 | B69: 수탁과제 | C69: 2025-013(R) | D69: 물부족 피해분석 및 물공급의 사회/경제적 가치 평가 기술 개발과 활용방안(3차년도) | F69: 10318 | G69: 이문환 | H69: 202508190 | I69: 물관리연구실 | J69: 182000000 | K69: 45658 | L69: 46022 | M69: 한국환경산업기술원 | N69: Development and Application of Techniques for Water Scarcity Damage Analysis and Socioeconomic Valuation of Water Supply (Year 3) | O69: =IFERROR(VLOOKUP($G69,'DB2'!$A:$B,2,0),"공동과책 확인") -> Lee, Moonhwan | P69: Water Management | Q69: Environmental Economics | R69: =IFERROR(VLOOKUP($I69,'DB2'!$F$2:$I$50,2,0),"옛날 부서명 확인") -> Water Management Division | S69: =IFERROR(VLOOKUP($I69,'DB2'!$F$2:$I$50,4,0),"옛날 부서명 확인") -> Land and Environment Research Group
A70: 71 | B70: 수탁과제 | C70: 2025-014(R) | D70: 탄소공간지도기반 계획지원 기술개발(3차년도) | F70: 10281 | G70: 김근한 | H70: 202508205 | I70: 국토관리연구실 | J70: 300000000 | K70: 45658 | L70: 46022 | M70: 국토교통과학기술진흥원 | N70: Technology Development for Supporting Carbon Mapping-Based Planning (Year 3) | O70: =IFERROR(VLOOKUP($G70,'DB2'!$A:$B,2,0),"공동과책 확인") -> Kim, Geunhan | P70: Land Management and Environment | Q70: Climate Environment (GHG Reduction) | R70: =IFERROR(VLOOKUP($I70,'DB2'!$F$2:$I$50,2,0),"옛날 부서명 확인") -> Spatial Planning and Management Division | S70: =IFERROR(VLOOKUP($I70,'DB2'!$F$2:$I$50,4,0),"옛날 부서명 확인") -> Land and Environment Research Group
A71: 72 | B71: 수탁과제 | C71: 2025-015(R) | D71: 습지생태계 기후변화 대응 평가·예측관리 기술 개발(4차년도) | F71: 10185 | G71: 명수정 | H71: 202508192 | I71: 자연환경연구실 | J71: 138600000 | K71: 45658 | L71: 46022 | M71: 한국환경산업기술원 | N71: Developing Technologies for Assessing and Predicting Wetland Ecosystem Responses to Climate Change (Year 4) | O71: =IFERROR(VLOOKUP($G71,'DB2'!$A:$B,2,0),"공동과책 확인") -> Myeong, Soojeong | P71: Ecology | Q71: Climate Adaptation | R71: =IFERROR(VLOOKUP($I71,'DB2'!$F$2:$I$50,2,0),"옛날 부서명 확인") -> Natural Environment Division | S71: =IFERROR(VLOOKUP($I71,'DB2'!$F$2:$I$50,4,0),"옛날 부서명 확인") -> Land and Environment Research Group
A72: 73 | B72: 수탁과제 | C72: 2025-016 | D72: 수자원 위성 활용기술 개발(Ⅱ)(2차) | F72: 30056 | G72: 이선민 | H72: 202508206 | I72: 사회기반평가실 | J72: 80742060 | K72: 45735 | L72: 46099 | M72: K-water 연구원 | N72: Developing Technologies for Water Resources Satellite Utilization (II) (Year 2) | O72: =IFERROR(VLOOKUP($G72,'DB2'!$A:$B,2,0),"공동과책 확인") -> Lee, Sunmin | P72: Water Management | Q72: Environmental Informatics | R72: =IFERROR(VLOOKUP($I72,'DB2'!$F$2:$I$50,2,0),"옛날 부서명 확인") -> Social Infrastructure Assessment Division | S72: =IFERROR(VLOOKUP($I72,'DB2'!$F$2:$I$50,4,0),"옛날 부서명 확인") -> Environmental Assessment Group
A73: 74 | B73: 수탁과제 | C73: 2025-017(R) | D73: AI 기반 도시침수 피해 위험도 예측 및 평가 실용화 기술 개발(2차년도) | F73: 10318 | G73: 이문환 | H73: 202508190 | I73: 물관리연구실 | J73: 258000000 | K73: 45658 | L73: 46022 | M73: 한국산업기술기획평가원 | N73: Developing AI-Based Practical Tools for Urban Flood Risk Prediction and Assessment (Year 2) | O73: =IFERROR(VLOOKUP($G73,'DB2'!$A:$B,2,0),"공동과책 확인") -> Lee, Moonhwan | P73: Water Management | Q73: Environmental Informatics | R73: =IFERROR(VLOOKUP($I73,'DB2'!$F$2:$I$50,2,0),"옛날 부서명 확인") -> Water Management Division | S73: =IFERROR(VLOOKUP($I73,'DB2'!$F$2:$I$50,4,0),"옛날 부서명 확인") -> Land and Environment Research Group
A74: 75 | B74: 수탁과제 | C74: 2025-018(R) | D74: 생태계서비스를 고려한 탄소흡수원 통합관리 플랫폼 기술개발(3차년도) | F74: 10185 | G74: 명수정 | H74: 202508192 | I74: 자연환경연구실 | J74: 100000000 | K74: 45658 | L74: 46022 | M74: 한국환경산업기술원 | N74: Developing an Integrated Management Platform for Carbon Sinks Incorporating Ecosystem Services (Year 3) | O74: =IFERROR(VLOOKUP($G74,'DB2'!$A:$B,2,0),"공동과책 확인") -> Myeong, Soojeong | P74: Climate Environment (GHG Reduction) | Q74: Ecology | R74: =IFERROR(VLOOKUP($I74,'DB2'!$F$2:$I$50,2,0),"옛날 부서명 확인") -> Natural Environment Division | S74: =IFERROR(VLOOKUP($I74,'DB2'!$F$2:$I$50,4,0),"옛날 부서명 확인") -> Land and Environment Research Group
A75: 76 | B75: 수탁과제 | C75: 2025-019(R) | D75: 해양산업시설 배출 위험유해물질 영향평가 및 관리기술 개발(5차년도) | F75: 10227 | G75: 김태윤 | H75: 202508165 | I75: 기후에너지평가실 | J75: 110000000 | K75: 45658 | L75: 46022 | M75: 해양수산과학기술진흥원 | N75: Developing Impact Assessment and Management Technologies for Hazardous Emissions from Marine Industrial Facilities (Year 5) | O75: =IFERROR(VLOOKUP($G75,'DB2'!$A:$B,2,0),"공동과책 확인") -> Kim, Taeyun | P75: Environmental Assessment | Q75: Marine Environment | R75: =IFERROR(VLOOKUP($I75,'DB2'!$F$2:$I$50,2,0),"옛날 부서명 확인") -> Climate and Energy Assessment Division | S75: =IFERROR(VLOOKUP($I75,'DB2'!$F$2:$I$50,4,0),"옛날 부서명 확인") -> Environmental Assessment Group
A76: 77 | B76: 수탁과제 | C76: 2025-020(R) | D76: 관측기반 온실가스 공간정보지도 구축 플랫폼 기술개발(3차년도) | F76: 10260 | G76: 이승민 | H76: 202508187 | I76: 대기환경연구실 | J76: 160000000 | K76: 45658 | L76: 46022 | M76: 한국환경산업기술원 | N76: Developing Technologies to Build an Observation-Based GHG Spatial Information Mapping Platform (Year 3) | O76: =IFERROR(VLOOKUP($G76,'DB2'!$A:$B,2,0),"공동과책 확인") -> Lee, Seungmin | P76: Climate Environment (GHG Reduction) | Q76: Environmental Informatics | R76: =IFERROR(VLOOKUP($I76,'DB2'!$F$2:$I$50,2,0),"옛날 부서명 확인") -> Atmospheric Environment Division | S76: =IFERROR(VLOOKUP($I76,'DB2'!$F$2:$I$50,4,0),"옛날 부서명 확인") -> Climate and Atmospheric Strategy Research Group
A77: 78 | B77: 수탁과제 | C77: 2025-021(R) | D77: 지역 맞춤형 초미세먼지 관리체계 개발(6차년도) | F77: 50021 | G77: 공성용 | H77: 201902187 | I77: 대기환경연구실 | J77: 15000000 | K77: 45658 | L77: 45747 | M77: 한국연구재단 | N77: Developing a Customized Regional PM2.5 Management System (Year 6) | O77: =IFERROR(VLOOKUP($G77,'DB2'!$A:$B,2,0),"공동과책 확인") -> Gong, Sungyong | P77: Atmospheric Environment | R77: =IFERROR(VLOOKUP($I77,'DB2'!$F$2:$I$50,2,0),"옛날 부서명 확인") -> Atmospheric Environment Division | S77: =IFERROR(VLOOKUP($I77,'DB2'!$F$2:$I$50,4,0),"옛날 부서명 확인") -> Climate and Atmospheric Strategy Research Group
A78: 79 | B78: 수탁과제 | C78: 2025-022 | D78: 섬진강 하류 재첩 서식환경 실증조사 연구(2차) | F78: 10343 | G78: 백동해 | H78: 202508163 | I78: 국토전략평가실 | J78: 127272730 | K78: 45672 | L78: 46095 | M78: 영산강유역환경청 | N78: Empirical Research of Corbicula japonica Habitats in the Lower Seomjin River (Phase 2) | O78: =IFERROR(VLOOKUP($G78,'DB2'!$A:$B,2,0),"공동과책 확인") -> Baek, Donghae | P78: Ecology | Q78: Water Management | R78: =IFERROR(VLOOKUP($I78,'DB2'!$F$2:$I$50,2,0),"옛날 부서명 확인") -> Land Strategy Assessment Division | S78: =IFERROR(VLOOKUP($I78,'DB2'!$F$2:$I$50,4,0),"옛날 부서명 확인") -> Environmental Assessment Group
A79: 80 | B79: 수탁과제 | C79: 2025-023 | D79: 제1차 국가물관리기본계획 2024년도 이행상황 평가 | F79: 10254 | G79: 류재나 | H79: 202508190 | I79: 물관리연구실 | J79: 98259300 | K79: 45674 | L79: 45972 | M79: 환경부 | N79: 2024 Progress Review of the First Master Plan for National Water Management | O79: =IFERROR(VLOOKUP($G79,'DB2'!$A:$B,2,0),"공동과책 확인") -> Ryu, Jaena | P79: Water Management | Q79: Land management and environment | R79: =IFERROR(VLOOKUP($I79,'DB2'!$F$2:$I$50,2,0),"옛날 부서명 확인") -> Water Management Division | S79: =IFERROR(VLOOKUP($I79,'DB2'!$F$2:$I$50,4,0),"옛날 부서명 확인") -> Land and Environment Research Group
A80: 81 | B80: 수탁과제 | C80: 2025-024 | D80: 국가물순환촉진기본방침 수립 및 실태조사 연구 | F80: 10203 | G80: 한혜진 | H80: 202508190 | I80: 물관리연구실 | J80: 308636360 | K80: 45681 | L80: 45980 | M80: 환경부 | N80: Development of the National Framework for Promoting Water Circulation and a Status Assessment | O80: =IFERROR(VLOOKUP($G80,'DB2'!$A:$B,2,0),"공동과책 확인") -> Han, Haejin | P80: Water Management | R80: =IFERROR(VLOOKUP($I80,'DB2'!$F$2:$I$50,2,0),"옛날 부서명 확인") -> Water Management Division | S80: =IFERROR(VLOOKUP($I80,'DB2'!$F$2:$I$50,4,0),"옛날 부서명 확인") -> Land and Environment Research Group
A81: 82 | B81: 수탁과제 | C81: 2025-025 | D81: 환경영향평가 제도개선 포럼 운영 | F81: 10289 | G81: 김경호 | H81: 202508206 | I81: 사회기반평가실 | J81: 49600000 | K81: 45695 | L81: 45994 | M81: 환경부 | N81: Operation of the Environmental Impact Assessment Reform Forum | O81: =IFERROR(VLOOKUP($G81,'DB2'!$A:$B,2,0),"공동과책 확인") -> Kim, Kyoung-Ho | P81: Environmental Assessment | R81: =IFERROR(VLOOKUP($I81,'DB2'!$F$2:$I$50,2,0),"옛날 부서명 확인") -> Social Infrastructure Assessment Division | S81: =IFERROR(VLOOKUP($I81,'DB2'!$F$2:$I$50,4,0),"옛날 부서명 확인") -> Environmental Assessment Group
A82: 83 | B82: 수탁과제 | C82: 2025-026 | D82: 국가 온실가스 장기 감축경로 마련을 위한 연구(2차) | F82: 10327 | G82: 김성진 | H82: 202508197 | I82: 탄소중립연구실 | J82: 272727270 | K82: 45685 | L82: 45895 | M82: 환경부 기후전략과 | N82: Developing National Long-Term Greenhouse Gas Reduction Pathways (Phase 2) | O82: =IFERROR(VLOOKUP($G82,'DB2'!$A:$B,2,0),"공동과책 확인") -> Kim, Sungjin | P82: Climate Environment (GHG Reduction) | R82: =IFERROR(VLOOKUP($I82,'DB2'!$F$2:$I$50,2,0),"옛날 부서명 확인") -> Carbon Neutrality Division | S82: =IFERROR(VLOOKUP($I82,'DB2'!$F$2:$I$50,4,0),"옛날 부서명 확인") -> Climate and Atmospheric Strategy Research Group
A83: 84 | B83: 수탁과제 | C83: 2025-027(R) | D83: 탁수의 수생태 영향 평가 및 예측 기술 개발(5차년도) | F83: 10356 | G83: 최미경 | H83: 202508190 | I83: 물관리연구실 | J83: 96000000 | K83: 45658 | L83: 46022 | M83: 한국환경산업기술원 | N83: Developing Technologies for Assessing and Predicting the Impacts of Turbidity on Aquatic Ecosystems (Year 5) | O83: =IFERROR(VLOOKUP($G83,'DB2'!$A:$B,2,0),"공동과책 확인") -> Choi, Mikyoung | P83: Water Management | Q83: Ecology | R83: =IFERROR(VLOOKUP($I83,'DB2'!$F$2:$I$50,2,0),"옛날 부서명 확인") -> Water Management Division | S83: =IFERROR(VLOOKUP($I83,'DB2'!$F$2:$I$50,4,0),"옛날 부서명 확인") -> Land and Environment Research Group
A84: 85 | B84: 수탁과제 | C84: 2025-028(R) | D84: 유역환경변화를 고려한 생태유량 취약성 평가 및 수질-수문-수생태 연계기술 개발(6차년도) | F84: 10205 | G84: 강형식 | H84: 202508182 | I84: 국토환경연구본부 | J84: 90000000 | K84: 45658 | L84: 46022 | M84: 한국환경산업기술원 | N84: Developing Technologies for Assessing Environmental Flow Vulnerability and Integrating Water Quality, Hydrology, and Aquatic Ecology Considering Watershed Environmental Changes (Year 6) | O84: =IFERROR(VLOOKUP($G84,'DB2'!$A:$B,2,0),"공동과책 확인") -> Kang, Hyeongsik | P84: Water Management | Q84: Ecology | R84: =IFERROR(VLOOKUP($I84,'DB2'!$F$2:$I$50,2,0),"옛날 부서명 확인") -> Land and Environment Research Group | S84: =IFERROR(VLOOKUP($I84,'DB2'!$F$2:$I$50,4,0),"옛날 부서명 확인") -> Land and Environment Research Group
A85: 86 | B85: 수탁과제 | C85: 2025-029 | D85: 차등화된 환경영향평가체계 마련 연구(2차) | F85: 10290 | G85: 양경 | H85: 202508165 | I85: 기후에너지평가실 | J85: 78600000 | K85: 45705 | L85: 46003 | M85: 환경부 | N85: Developing a Tiered Environmental Impact Assessment System (Phase 2) | O85: =IFERROR(VLOOKUP($G85,'DB2'!$A:$B,2,0),"공동과책 확인") -> Yang, Kyung | P85: Environmental Assessment | R85: =IFERROR(VLOOKUP($I85,'DB2'!$F$2:$I$50,2,0),"옛날 부서명 확인") -> Climate and Energy Assessment Division | S85: =IFERROR(VLOOKUP($I85,'DB2'!$F$2:$I$50,4,0),"옛날 부서명 확인") -> Environmental Assessment Group
A86: 87 | B86: 수탁과제 | C86: 2025-030(R) | D86: 글로벌 탄소중립 선도도시 도약을 위한 해수이용 친환경 에너지저장 핵심기술개발(4차년도) | F86: 10166 | G86: 조한나 | H86: 202508123 | I86: 기후적응협력실 | J86: 100000000 | K86: 45658 | L86: 46022 | M86: 연구개발특구진흥재단 | N86: Development of Core Technologies for Eco-Friendly Seawater-Based Energy Storage to Advance Leading Global Carbon-Neutral Cities (Year 4) | O86: =IFERROR(VLOOKUP($G86,'DB2'!$A:$B,2,0),"공동과책 확인") -> Cho, Hanna | P86: Climate Environment (GHG Reduction) | Q86: Marine Environment | R86: =IFERROR(VLOOKUP($I86,'DB2'!$F$2:$I$50,2,0),"옛날 부서명 확인") -> Climate Adaptation Cooperation Division | S86: =IFERROR(VLOOKUP($I86,'DB2'!$F$2:$I$50,4,0),"옛날 부서명 확인") -> Korea Adaptation Center for Climate Change
A87: 88 | B87: 수탁과제 | C87: 2025-031(R) | D87: 하천의 물리적 환경변화 고려 하천종단 수자원시설의 치수안전도 평가 기술개발(2차년도) | F87: 10205 | G87: 강형식 | H87: 202508182 | I87: 국토환경연구본부 | J87: 154600000 | K87: 45658 | L87: 46022 | M87: 한국환경산업기술원 | N87: Development of Technologies for Assessing Flood Safety of Longitudinal River Water Infrastructure Considering Physical Changes in River Environments (Year 2) | O87: =IFERROR(VLOOKUP($G87,'DB2'!$A:$B,2,0),"공동과책 확인") -> Kang, Hyeongsik | P87: Water Management | Q87: Climate Adaptation | R87: =IFERROR(VLOOKUP($I87,'DB2'!$F$2:$I$50,2,0),"옛날 부서명 확인") -> Land and Environment Research Group | S87: =IFERROR(VLOOKUP($I87,'DB2'!$F$2:$I$50,4,0),"옛날 부서명 확인") -> Land and Environment Research Group
A88: 89 | B88: 수탁과제 | C88: 2025-032(R) | D88: 기후변화 대응을 위한 농축산부문 2030 NDC 온실가스 감축 이행 평가(2차년도) | F88: 10185 | G88: 명수정 | H88: 202508192 | I88: 자연환경연구실 | J88: 58000000 | K88: 45658 | L88: 46022 | M88: 농촌진흥청 | N88: Evaluation of Greenhouse Gas Reduction under the 2030 NDC in the Agriculture and Livestock Sector (Year 2) | O88: =IFERROR(VLOOKUP($G88,'DB2'!$A:$B,2,0),"공동과책 확인") -> Myeong, Soojeong | P88: Climate Environment (GHG Reduction) | R88: =IFERROR(VLOOKUP($I88,'DB2'!$F$2:$I$50,2,0),"옛날 부서명 확인") -> Natural Environment Division | S88: =IFERROR(VLOOKUP($I88,'DB2'!$F$2:$I$50,4,0),"옛날 부서명 확인") -> Land and Environment Research Group
A89: 90 | B89: 수탁과제 | C89: 2025-033 | D89: 무탄소 전원 환경성평가 방안 연구 | F89: 10227 | G89: 김태윤 | H89: 202508165 | I89: 기후에너지평가실 | J89: 170000000 | K89: 45715 | L89: 46022 | M89: 환경부 환경영향평가과 | N89: Developing Environmental Assessment Approaches for Zero-Carbon Power Sources | O89: =IFERROR(VLOOKUP($G89,'DB2'!$A:$B,2,0),"공동과책 확인") -> Kim, Taeyun | P89: Environmental Assessment | Q89: Climate Environment (GHG Reduction) | R89: =IFERROR(VLOOKUP($I89,'DB2'!$F$2:$I$50,2,0),"옛날 부서명 확인") -> Climate and Energy Assessment Division | S89: =IFERROR(VLOOKUP($I89,'DB2'!$F$2:$I$50,4,0),"옛날 부서명 확인") -> Environmental Assessment Group
A90: 91 | B90: 수탁과제 | C90: 2025-034 | D90: 환경성보장제 운영을 위한 전기·전자제품 분류 및 분석 | F90: 10273 | G90: 이소라 | H90: 202508204 | I90: 순환경제연구실 | J90: 152000000 | K90: 45712 | L90: 45982 | M90: 한국환경공단 | N90: Classification and Analysis of Electrical and Electronic Products to Promote the Eco-Assurance System (EcoAS) | O90: =IFERROR(VLOOKUP($G90,'DB2'!$A:$B,2,0),"공동과책 확인") -> Yi, Sora | P90: Circular Economy | R90: =IFERROR(VLOOKUP($I90,'DB2'!$F$2:$I$50,2,0),"옛날 부서명 확인") -> Circular Economy Division | S90: =IFERROR(VLOOKUP($I90,'DB2'!$F$2:$I$50,4,0),"옛날 부서명 확인") -> Sustainable Development Research Group
A91: 92 | B91: 수탁과제 | C91: 2025-035(R) | D91: 홍수피해 유형화 기반 취약지역 평가 및 피해액 추정 모형 개발 연구(3차년도) | F91: 10333 | G91: 정기철 | H91: 202508190 | I91: 물관리연구실 | J91: 89350000 | K91: 45717 | L91: 46081 | M91: 한국연구재단 | N91: Study on Developing a System for Flood Risk Evaluation and Expected Annual Damage based on Flood Damage Types (Year 3) | O91: =IFERROR(VLOOKUP($G91,'DB2'!$A:$B,2,0),"공동과책 확인") -> Jung, Kichul | P91: Water Management | Q91: Environmental Economics | R91: =IFERROR(VLOOKUP($I91,'DB2'!$F$2:$I$50,2,0),"옛날 부서명 확인") -> Water Management Division | S91: =IFERROR(VLOOKUP($I91,'DB2'!$F$2:$I$50,4,0),"옛날 부서명 확인") -> Land and Environment Research Group
A92: 93 | B92: 수탁과제 | C92: 2025-036 | D92: 전북 서해안 세계지질공원 재검증 및 확대 인증 용역 | F92: 50018 | G92: 이수재 | H92: 202508192 | I92: 자연환경연구실 | J92: 130895000 | K92: 45730 | L92: 46389 | M92: 전북특별자치도 | N92: Study for Revalidation and Expansion of the Jeonbuk West Coast UNESCO Global Geopark | O92: =IFERROR(VLOOKUP($G92,'DB2'!$A:$B,2,0),"공동과책 확인") -> Lee, Soojae | P92: Ecology | Q92: Land management and environment | R92: =IFERROR(VLOOKUP($I92,'DB2'!$F$2:$I$50,2,0),"옛날 부서명 확인") -> Natural Environment Division | S92: =IFERROR(VLOOKUP($I92,'DB2'!$F$2:$I$50,4,0),"옛날 부서명 확인") -> Land and Environment Research Group
A93: 94 | B93: 수탁과제 | C93: 2025-037 | D93: 제5차 소음·진동관리종합계획 수립 연구 | F93: 10337 | G93: 박태호 | H93: 202508206 | I93: 사회기반평가실 | J93: 90000000 | K93: 45723 | L93: 46006 | M93: 환경부 | N93: Study on the Formulation of the Fifth Comprehensive Noise and Vibration Management Plan | O93: =IFERROR(VLOOKUP($G93,'DB2'!$A:$B,2,0),"공동과책 확인") -> Park, Taeho | P93: Noise and Vibration Impacts | R93: =IFERROR(VLOOKUP($I93,'DB2'!$F$2:$I$50,2,0),"옛날 부서명 확인") -> Social Infrastructure Assessment Division | S93: =IFERROR(VLOOKUP($I93,'DB2'!$F$2:$I$50,4,0),"옛날 부서명 확인") -> Environmental Assessment Group
A94: 95 | B94: 수탁과제 | C94: 2025-038 | D94: 국토-환경계획 통합관리 이행 고도화 및 시범사업 운영 | F94: 10283 | G94: 송지윤 | H94: 202508124 | I94: 기후적응정책실 | J94: 78856000 | K94: 45723 | L94: 46022 | M94: 환경부 | N94: Advancing Integrated Management of Land and Environmental Planning and Operating Pilot Projects | O94: =IFERROR(VLOOKUP($G94,'DB2'!$A:$B,2,0),"공동과책 확인") -> Song, Jiyoon | P94: Land Management and Environment | R94: =IFERROR(VLOOKUP($I94,'DB2'!$F$2:$I$50,2,0),"옛날 부서명 확인") -> Climate Adaptation Policy Division | S94: =IFERROR(VLOOKUP($I94,'DB2'!$F$2:$I$50,4,0),"옛날 부서명 확인") -> Korea Adaptation Center for Climate Change
A95: 96 | B95: 수탁과제 | C95: 2025-039 | D95: 협의권한 지방이양 특례 운영성과 평가 연구(환경영향평가, 자연경관영향협의 부문) | F95: 10245 | G95: 이상윤 | H95: 202508207 | I95: 환경자원평가실 | J95: 39550000 | K95: 45726 | L95: 45995 | M95: 환경부 | N95: Evaluating the Outcomes of Special Local Transfers of Consultation Authority (EIA and Landscape Consultation Sectors) | O95: =IFERROR(VLOOKUP($G95,'DB2'!$A:$B,2,0),"공동과책 확인") -> Lee, Sangyun | P95: Environmental Assessment | R95: =IFERROR(VLOOKUP($I95,'DB2'!$F$2:$I$50,2,0),"옛날 부서명 확인") -> Environmental Resources Assessment Division | S95: =IFERROR(VLOOKUP($I95,'DB2'!$F$2:$I$50,4,0),"옛날 부서명 확인") -> Environmental Assessment Group
A96: 97 | B96: 수탁과제 | C96: 2025-040 | D96: 국토환경 녹색복원 후보목록 3차년도 조사연구 | F96: 10282 | G96: 손승우 | H96: 202508205 | I96: 국토관리연구실 | J96: 143600000 | K96: 45722 | L96: 46086 | M96: 환경부 | N96: Developing a National Candidate Site List for Green Restoration (Year 3) | O96: =IFERROR(VLOOKUP($G96,'DB2'!$A:$B,2,0),"공동과책 확인") -> Son, Seungwoo | P96: Land Management and Environment | Q96: Ecology | R96: =IFERROR(VLOOKUP($I96,'DB2'!$F$2:$I$50,2,0),"옛날 부서명 확인") -> Spatial Planning and Management Division | S96: =IFERROR(VLOOKUP($I96,'DB2'!$F$2:$I$50,4,0),"옛날 부서명 확인") -> Land and Environment Research Group
A97: 98 | B97: 수탁과제 | C97: 2025-041 | D97: 빛공해 방지법 미적용 조명 관리방안 마련 연구 | F97: 10152 | G97: 이상범 | H97: 202508102 | I97: 환경평가본부 | J97: 39600000 | K97: 45727 | L97: 45989 | M97: 환경부 | N97: Developing Management Approaches for Lighting Outside the Scope of the Light Pollution Prevention Act | O97: =IFERROR(VLOOKUP($G97,'DB2'!$A:$B,2,0),"공동과책 확인") -> Lee, Sangbum | P97: Noise and Vibration Impacts | Q97: Environmental Assessment | R97: =IFERROR(VLOOKUP($I97,'DB2'!$F$2:$I$50,2,0),"옛날 부서명 확인") -> Environmental Assessment Group | S97: =IFERROR(VLOOKUP($I97,'DB2'!$F$2:$I$50,4,0),"옛날 부서명 확인") -> Environmental Assessment Group
A98: 99 | B98: 수탁과제 | C98: 2025-042(R) | D98: 딥러닝 기반 생물다양성 예측 및 리질리언스 평가 기술 개발(5차년도) | F98: 10346 | G98: 최유영 | H98: 202508163 | I98: 국토전략평가실 | J98: 119950000 | K98: 45717 | L98: 46535 | M98: 한국연구재단 | N98: Resilience Assessment of Biodiversity Using Bigdata and Intelligent Technology (RABBIT) (Year 5) | O98: =IFERROR(VLOOKUP($G98,'DB2'!$A:$B,2,0),"공동과책 확인") -> Choi, Yuyoung | P98: Environmental Informatics | Q98: Ecology | R98: =IFERROR(VLOOKUP($I98,'DB2'!$F$2:$I$50,2,0),"옛날 부서명 확인") -> Land Strategy Assessment Division | S98: =IFERROR(VLOOKUP($I98,'DB2'!$F$2:$I$50,4,0),"옛날 부서명 확인") -> Environmental Assessment Group
A99: 100 | B99: 수탁과제 | C99: 2025-043 | D99: 협의권한 지방이양 특례 운영성과 평가 연구(기후변화영향평가 부문) | F99: 10245 | G99: 이상윤 | H99: 202508207 | I99: 환경자원평가실 | J99: 39700000 | K99: 45729 | L99: 45998 | M99: 환경부 | N99: Evaluating the Outcomes of Special Local Transfers of Consultation Authority (Climate Change Impact Assessment Sector) | O99: =IFERROR(VLOOKUP($G99,'DB2'!$A:$B,2,0),"공동과책 확인") -> Lee, Sangyun | P99: Environmental Assessment | R99: =IFERROR(VLOOKUP($I99,'DB2'!$F$2:$I$50,2,0),"옛날 부서명 확인") -> Environmental Resources Assessment Division | S99: =IFERROR(VLOOKUP($I99,'DB2'!$F$2:$I$50,4,0),"옛날 부서명 확인") -> Environmental Assessment Group
A100: 101 | B100: 수탁과제 | C100: 2025-044 | D100: 발전부문 BM기반 사전할당에 따른 영향분석 연구 | F100: 10334 | G100: 최형식 | H100: 202508197 | I100: 탄소중립연구실 | J100: 79100000 | K100: 45730 | L100: 45970 | M100: 환경부 기후경제과 | N100: Study on the Effects of BM-Based Pre-Allocation in the Power Sector | O100: =IFERROR(VLOOKUP($G100,'DB2'!$A:$B,2,0),"공동과책 확인") -> Choi, Hyungsik | P100: Climate Environment (GHG Reduction) | Q100: Environmental Economics | R100: =IFERROR(VLOOKUP($I100,'DB2'!$F$2:$I$50,2,0),"옛날 부서명 확인") -> Carbon Neutrality Division | S100: =IFERROR(VLOOKUP($I100,'DB2'!$F$2:$I$50,4,0),"옛날 부서명 확인") -> Climate and Atmospheric Strategy Research Group
A101: 102 | B101: 수탁과제 | C101: 2025-045 | D101: 국가생물다양성전략 이행점검을 위한 지표 개발 연구(2차년도) | F101: 10300 | G101: 구경아 | H101: 202508192 | I101: 자연환경연구실 | J101: 130454540 | K101: 45734 | L101: 45991 | M101: 국립생물자원관 | N101: Indicator Development for Assessing the Implementation of the National Biodiversity Strategy (Year 2) | O101: =IFERROR(VLOOKUP($G101,'DB2'!$A:$B,2,0),"공동과책 확인") -> Koo, Kyung Ah | P101: Ecology | R101: =IFERROR(VLOOKUP($I101,'DB2'!$F$2:$I$50,2,0),"옛날 부서명 확인") -> Natural Environment Division | S101: =IFERROR(VLOOKUP($I101,'DB2'!$F$2:$I$50,4,0),"옛날 부서명 확인") -> Land and Environment Research Group
A102: 103 | B102: 수탁과제 | C102: 2025-046 | D102: 녹색산업계정 시범편제 연구 | F102: 10139 | G102: 김종호 | H102: 202508204 | I102: 순환경제연구실 | J102: 227270000 | K102: 45747 | L102: 46022 | M102: 환경부 녹색기술개발과 | N102: Pilot Compilation of Environmental Goods and Services Sector Accounts | O102: =IFERROR(VLOOKUP($G102,'DB2'!$A:$B,2,0),"공동과책 확인") -> Kim, Jongho | P102: Environmental Economics | Q102: Environmental Informatics | R102: =IFERROR(VLOOKUP($I102,'DB2'!$F$2:$I$50,2,0),"옛날 부서명 확인") -> Circular Economy Division | S102: =IFERROR(VLOOKUP($I102,'DB2'!$F$2:$I$50,4,0),"옛날 부서명 확인") -> Sustainable Development Research Group
...

Sheet DB2
A1: 성명 | B1: 성명(영문) | F1: 실 | H1: 부
A2: 김영란 | B2: Kim, Youngran | F2: 기후적응정책실 | G2: Climate Adaptation Policy Division | H2: 국가기후위기적응센터 | I2: Korea Adaptation Center for Climate Change
A3: 장기복 | B3: Chang, Ki-bok | F3: 국가기후위기적응센터 | G3: Korea Adaptation Center for Climate Change | H3: 국가기후위기적응센터 | I3: Korea Adaptation Center for Climate Change
A4: 박정규 | B4: Park, Jeonggue | F4: 기후적응협력실 | G4: Climate Adaptation Cooperation Division | H4: 국가기후위기적응센터 | I4: Korea Adaptation Center for Climate Change
A5: 이영수 | B5: Lee, Youngsoo | F5: 국토환경연구본부 | G5: Land and Environment Research Group | H5: 국토환경연구본부 | I5: Land and Environment Research Group
A6: 맹준호 | B6: Maeng, Junho | F6: 자연환경연구실 | G6: Natural Environment Division | H6: 국토환경연구본부 | I6: Land and Environment Research Group
A7: 주현수 | B7: Joo, Hyun-soo | F7: 국토관리연구실 | G7: Spatial Planning and Management Division | H7: 국토환경연구본부 | I7: Land and Environment Research Group
A8: 윤정호 | B8: Yoon, Jeongho | F8: 물관리연구실 | G8: Water Management Division | H8: 국토환경연구본부 | I8: Land and Environment Research Group
A9: 최두연 | B9: Choi, Dooyeon | F9: AI데이터팀 | G9: AI and Data Team | H9: 기획조정실 | I9: Department of Planning and Strategy
A10: 정태영 | B10: Chung, Taeyoung | F10: 글로벌협력팀 | G10: Global Cooperation Team | H10: 기획조정실 | I10: Department of Planning and Strategy
A11: 김용구 | B11: Kim, Yonggu | F11: 성과관리팀 | G11: Performance Management Team | H11: 기획조정실 | I11: Department of Planning and Strategy
A12: 송은상 | B12: Song, Eunsang | F12: 녹색경제연구실 | G12: Green Economy Division | H12: 기후대기전략연구본부 | I12: Climate and Atmospheric Strategy Research Group
A13: 주용준 | B13: Joo, Yong-Joon | F13: 대기환경연구실 | G13: Atmospheric Environment Division | H13: 기후대기전략연구본부 | I13: Climate and Atmospheric Strategy Research Group
... A25: 조공장 | B25: Cho, Kongjang | F25: 국토전략평가실 | G25: Land Strategy Assessment Division | H25: 환경평가본부 | I25: Environmental Assessment Group
A26: 사공희 | B26: Sagong, Hee
A27: 전동준 | B27: Chun, Dongjun
A28: 신지영 | B28: Shin, Jiyoung | F28: 1. 연구현황에서 엑셀 다운로드 받아서 추가할 과제만 추려서 디비1에 붙여넣기
A29: 임혜숙 | B29: Lim, Hyesook | F29: -> 열 수정하면 안됨, 필요한 행만 가져와서 붙여넣어야함.
A30: 박하늘 | B30: Park, Ha-neul | F30: 2. 붙여넣고 나면 부서명이 옛날거라서 디비1에서 오류메시지 나올 수 있음 -> 수정
A31: 하종식 | B31: Ha, Jongsik | F31: 3. 붙여넣고 나면 과제책임자가 두명이라서 디비1에서 오류메시지 나올 수 있음 -> 수정
A32: 이명진 | B32: Lee, MoungJin | F32: 4. 디비2에서 각 사람별 영문명 추가 및 수정
A33: 홍현정 | B33: Hong, Hyunjung | F33: 5. 디비2에서 실, 본부별 영문명 추가 및 수정
A34: 조한나 | B34: Cho, Hanna
A35: 양일주 | B35: Yang, Iljoo
A36: 정선희 | B36: Jung, Seonhee
A37: 문준영 | B37: Moon, Junyoung
A38: 이상엽 | B38: Lee, Sangyoup
A39: 김호석 | B39: Kim, Hoseok
A40: 한상운 | B40: Han, Sangun
A41: 김태형 | B41: Kim, Taehyoung
A42: 임영신 | B42: Lim, Youngshin
A43: 이영미 | B43: Lee, Youngmi | F43: Working Paper | G43: BA
A44: 김익재 | B44: Kim, Ikjae | F44: General Project | G44: GP | H44: RR | I44: RI | J44: SP
A45: 명수정 | B45: Myeong, Soojeong | F45: Core Research | G45: RE
A46: 최희선 | B46: Choi, Hee-Sun | F46: Policy Issue Study | G46: WO
A47: 한대호 | B47: Han, Daeho | F47: Commissioned Research | G47: 20
A48: 조일현 | B48: Cho, Ilhyun
A49: 신상철 | B49: Shin, Sang-Cheol
A50: 안종호 | B50: Ahn, Jongho
A51: 이진희 | B51: Lee, Jinhee
A52: 김영인 | B52: Kim, Youngin
A53: 조을생 | B53: Cho, Eulsaeng
A54: 심창섭 | B54: Shim, Changsub
A55: 이정석 | B55: Lee, Jeongseok
A56: 한혜진 | B56: Han, Haejin
A57: 강형식 | B57: Kang, Hyeongsik
A58: 정휘철 | B58: Jung, Huicheul
A59: 배현주 | B59: Bae, Hyun-Joo
... A305: 김택건 | B305: Kim, Taeg Keon
A306: 김태우
A307: 이지민 | B307: Lee, Jimin
A308: 이주양 | B308: Lee, Juyang
A309: 노정담 | B309: Noh, Jeongdam
A310: 권예진 | B310: Kwon, Yejin
A311: 신경희 | B311: Shin, Kyunghee
A312: 박준현 | B312: Park, Jun Hyun
A313: 정벼리 | B313: Jung, Byuree
A314: 정성운 | B314: Jung, Sungwoon
A315: 공지영 | B315: Gong, Jiyoung
A316: 서양원 | B316: Suh, Yang-won
A317: 김이진 | B317: Kim, Leejin
A318: 김이진 | B318: Kim, Leejin
... A323: 강유진 | B323: Kang, Eugene
